{
  "ts": 1784138858849,
  "source": "github-cron",
  "count": 244,
  "skipped": 3,
  "universe_size": 247,
  "data": [
    {
      "t": "AAPL",
      "gex": 301.6,
      "gexProxy": false,
      "flip": 310.0,
      "flipSrc": "gamma",
      "call": 70,
      "put": 30,
      "callOI": 346935,
      "putOI": 220018,
      "callVol": 127297,
      "putVol": 26087,
      "dte": 37,
      "exp": "2026-08-21",
      "price": 327.57,
      "flow": "CALL HEAVY",
      "flowCls": "go"
    },
    {
      "t": "MSFT",
      "gex": 253.0,
      "gexProxy": false,
      "flip": 400.0,
      "flipSrc": "gamma",
      "call": 81,
      "put": 19,
      "callOI": 594219,
      "putOI": 159088,
      "callVol": 28792,
      "putVol": 6061,
      "dte": 37,
      "exp": "2026-08-21",
      "price": 395.81,
      "flow": "CALL HEAVY",
      "flowCls": "go"
    },
    {
      "t": "META",
      "gex": 164.3,
      "gexProxy": false,
      "flip": 665.0,
      "flipSrc": "gamma",
      "call": 75,
      "put": 25,
      "callOI": 190508,
      "putOI": 98160,
      "callVol": 33972,
      "putVol": 4487,
      "dte": 37,
      "exp": "2026-08-21",
      "price": 676.41,
      "flow": "CALL HEAVY",
      "flowCls": "go"
    },
    {
      "t": "AMZN",
      "gex": 164.0,
      "gexProxy": false,
      "flip": 260.0,
      "flipSrc": "gamma",
      "call": 75,
      "put": 25,
      "callOI": 528905,
      "putOI": 209826,
      "callVol": 35658,
      "putVol": 9260,
      "dte": 37,
      "exp": "2026-08-21",
      "price": 254.84,
      "flow": "CALL HEAVY",
      "flowCls": "go"
    },
    {
      "t": "GOOGL",
      "gex": 92.0,
      "gexProxy": false,
      "flip": 400.0,
      "flipSrc": "gamma",
      "call": 76,
      "put": 24,
      "callOI": 248895,
      "putOI": 145278,
      "callVol": 96618,
      "putVol": 4916,
      "dte": 37,
      "exp": "2026-08-21",
      "price": 371.94,
      "flow": "CALL HEAVY",
      "flowCls": "go"
    },
    {
      "t": "NVDA",
      "gex": 71.2,
      "gexProxy": false,
      "flip": 230.0,
      "flipSrc": "gamma",
      "call": 63,
      "put": 37,
      "callOI": 613977,
      "putOI": 507413,
      "callVol": 67902,
      "putVol": 21719,
      "dte": 37,
      "exp": "2026-08-21",
      "price": 209.98,
      "flow": "CALL HEAVY",
      "flowCls": "go"
    },
    {
      "t": "GS",
      "gex": 34.4,
      "gexProxy": false,
      "flip": 1100.0,
      "flipSrc": "gamma",
      "call": 57,
      "put": 43,
      "callOI": 21854,
      "putOI": 18482,
      "callVol": 1051,
      "putVol": 674,
      "dte": 37,
      "exp": "2026-08-21",
      "price": 1142.98,
      "flow": "CALL HEAVY",
      "flowCls": "go"
    },
    {
      "t": "JPM",
      "gex": 34.2,
      "gexProxy": false,
      "flip": 340.0,
      "flipSrc": "gamma",
      "call": 50,
      "put": 50,
      "callOI": 38681,
      "putOI": 45871,
      "callVol": 2938,
      "putVol": 2211,
      "dte": 37,
      "exp": "2026-08-21",
      "price": 347.81,
      "flow": "CALL HEAVY",
      "flowCls": "go"
    },
    {
      "t": "GOOG",
      "gex": 31.5,
      "gexProxy": false,
      "flip": 375.0,
      "flipSrc": "gamma",
      "call": 65,
      "put": 35,
      "callOI": 107036,
      "putOI": 88901,
      "callVol": 9896,
      "putVol": 2487,
      "dte": 37,
      "exp": "2026-08-21",
      "price": 370.77,
      "flow": "CALL HEAVY",
      "flowCls": "go"
    },
    {
      "t": "AMD",
      "gex": 27.7,
      "gexProxy": false,
      "flip": 300.0,
      "flipSrc": "gamma",
      "call": 56,
      "put": 44,
      "callOI": 139318,
      "putOI": 142276,
      "callVol": 11209,
      "putVol": 5876,
      "dte": 37,
      "exp": "2026-08-21",
      "price": 531.02,
      "flow": "CALL HEAVY",
      "flowCls": "go"
    },
    {
      "t": "XLE",
      "gex": 23.3,
      "gexProxy": false,
      "flip": 58.0,
      "flipSrc": "gamma",
      "call": 64,
      "put": 36,
      "callOI": 221836,
      "putOI": 179524,
      "callVol": 15450,
      "putVol": 4465,
      "dte": 37,
      "exp": "2026-08-21",
      "price": 56.09,
      "flow": "CALL HEAVY",
      "flowCls": "go"
    },
    {
      "t": "UNH",
      "gex": 22.0,
      "gexProxy": false,
      "flip": 400.0,
      "flipSrc": "gamma",
      "call": 51,
      "put": 49,
      "callOI": 39712,
      "putOI": 43749,
      "callVol": 1897,
      "putVol": 1582,
      "dte": 37,
      "exp": "2026-08-21",
      "price": 420.36,
      "flow": "CALL HEAVY",
      "flowCls": "go"
    },
    {
      "t": "LLY",
      "gex": 21.5,
      "gexProxy": false,
      "flip": 1200.0,
      "flipSrc": "gamma",
      "call": 56,
      "put": 44,
      "callOI": 18593,
      "putOI": 12808,
      "callVol": 1034,
      "putVol": 993,
      "dte": 37,
      "exp": "2026-08-21",
      "price": 1152.0,
      "flow": "CALL HEAVY",
      "flowCls": "go"
    },
    {
      "t": "ABBV",
      "gex": 21.4,
      "gexProxy": false,
      "flip": 240.0,
      "flipSrc": "gamma",
      "call": 67,
      "put": 33,
      "callOI": 30119,
      "putOI": 15641,
      "callVol": 440,
      "putVol": 196,
      "dte": 37,
      "exp": "2026-08-21",
      "price": 246.5,
      "flow": "CALL HEAVY",
      "flowCls": "go"
    },
    {
      "t": "V",
      "gex": 18.6,
      "gexProxy": false,
      "flip": 345.0,
      "flipSrc": "gamma",
      "call": 62,
      "put": 38,
      "callOI": 22286,
      "putOI": 19038,
      "callVol": 915,
      "putVol": 309,
      "dte": 37,
      "exp": "2026-08-21",
      "price": 357.64,
      "flow": "CALL HEAVY",
      "flowCls": "go"
    },
    {
      "t": "TSLA",
      "gex": 16.5,
      "gexProxy": false,
      "flip": 475.0,
      "flipSrc": "gamma",
      "call": 62,
      "put": 38,
      "callOI": 213584,
      "putOI": 170055,
      "callVol": 18086,
      "putVol": 7688,
      "dte": 37,
      "exp": "2026-08-21",
      "price": 399.25,
      "flow": "CALL HEAVY",
      "flowCls": "go"
    },
    {
      "t": "JNJ",
      "gex": 11.1,
      "gexProxy": false,
      "flip": 250.0,
      "flipSrc": "gamma",
      "call": 75,
      "put": 25,
      "callOI": 18286,
      "putOI": 10159,
      "callVol": 14318,
      "putVol": 1201,
      "dte": 37,
      "exp": "2026-08-21",
      "price": 248.2,
      "flow": "CALL HEAVY",
      "flowCls": "go"
    },
    {
      "t": "BABA",
      "gex": 10.1,
      "gexProxy": false,
      "flip": 65.0,
      "flipSrc": "gamma",
      "call": 68,
      "put": 32,
      "callOI": 107271,
      "putOI": 59681,
      "callVol": 14296,
      "putVol": 4760,
      "dte": 37,
      "exp": "2026-08-21",
      "price": 118.52,
      "flow": "CALL HEAVY",
      "flowCls": "go"
    },
    {
      "t": "GILD",
      "gex": 10.1,
      "gexProxy": false,
      "flip": 135.0,
      "flipSrc": "gamma",
      "call": 76,
      "put": 24,
      "callOI": 32979,
      "putOI": 5074,
      "callVol": 997,
      "putVol": 682,
      "dte": 37,
      "exp": "2026-08-21",
      "price": 131.93,
      "flow": "CALL HEAVY",
      "flowCls": "go"
    },
    {
      "t": "USO",
      "gex": 9.5,
      "gexProxy": false,
      "flip": 111.0,
      "flipSrc": "gamma",
      "call": 70,
      "put": 30,
      "callOI": 51142,
      "putOI": 18070,
      "callVol": 3481,
      "putVol": 1952,
      "dte": 37,
      "exp": "2026-08-21",
      "price": 119.52,
      "flow": "CALL HEAVY",
      "flowCls": "go"
    },
    {
      "t": "BAC",
      "gex": 9.2,
      "gexProxy": false,
      "flip": 57.5,
      "flipSrc": "gamma",
      "call": 56,
      "put": 44,
      "callOI": 65638,
      "putOI": 73725,
      "callVol": 7856,
      "putVol": 3298,
      "dte": 37,
      "exp": "2026-08-21",
      "price": 61.48,
      "flow": "CALL HEAVY",
      "flowCls": "go"
    },
    {
      "t": "CRM",
      "gex": 9.0,
      "gexProxy": false,
      "flip": 180.0,
      "flipSrc": "gamma",
      "call": 66,
      "put": 34,
      "callOI": 98962,
      "putOI": 56455,
      "callVol": 13289,
      "putVol": 6046,
      "dte": 37,
      "exp": "2026-08-21",
      "price": 167.1,
      "flow": "CALL HEAVY",
      "flowCls": "go"
    },
    {
      "t": "C",
      "gex": 8.7,
      "gexProxy": false,
      "flip": 140.0,
      "flipSrc": "gamma",
      "call": 73,
      "put": 27,
      "callOI": 50365,
      "putOI": 34575,
      "callVol": 17620,
      "putVol": 1164,
      "dte": 37,
      "exp": "2026-08-21",
      "price": 134.35,
      "flow": "CALL HEAVY",
      "flowCls": "go"
    },
    {
      "t": "XOM",
      "gex": 8.2,
      "gexProxy": false,
      "flip": 145.0,
      "flipSrc": "gamma",
      "call": 73,
      "put": 27,
      "callOI": 45763,
      "putOI": 20460,
      "callVol": 5598,
      "putVol": 1464,
      "dte": 37,
      "exp": "2026-08-21",
      "price": 143.27,
      "flow": "CALL HEAVY",
      "flowCls": "go"
    },
    {
      "t": "CRWD",
      "gex": 8.1,
      "gexProxy": false,
      "flip": 105.0,
      "flipSrc": "gamma",
      "call": 56,
      "put": 44,
      "callOI": 90743,
      "putOI": 84091,
      "callVol": 5174,
      "putVol": 3114,
      "dte": 37,
      "exp": "2026-08-21",
      "price": 207.7,
      "flow": "CALL HEAVY",
      "flowCls": "go"
    },
    {
      "t": "UPS",
      "gex": 7.8,
      "gexProxy": false,
      "flip": 110.0,
      "flipSrc": "gamma",
      "call": 77,
      "put": 23,
      "callOI": 29408,
      "putOI": 11212,
      "callVol": 1517,
      "putVol": 286,
      "dte": 37,
      "exp": "2026-08-21",
      "price": 114.28,
      "flow": "CALL HEAVY",
      "flowCls": "go"
    },
    {
      "t": "HOOD",
      "gex": 7.6,
      "gexProxy": false,
      "flip": 100.0,
      "flipSrc": "gamma",
      "call": 65,
      "put": 35,
      "callOI": 103800,
      "putOI": 101311,
      "callVol": 9751,
      "putVol": 1659,
      "dte": 37,
      "exp": "2026-08-21",
      "price": 115.65,
      "flow": "CALL HEAVY",
      "flowCls": "go"
    },
    {
      "t": "MA",
      "gex": 7.6,
      "gexProxy": false,
      "flip": 540.0,
      "flipSrc": "gamma",
      "call": 63,
      "put": 37,
      "callOI": 6652,
      "putOI": 6566,
      "callVol": 567,
      "putVol": 116,
      "dte": 37,
      "exp": "2026-08-21",
      "price": 536.2,
      "flow": "CALL HEAVY",
      "flowCls": "go"
    },
    {
      "t": "SLV",
      "gex": 7.5,
      "gexProxy": false,
      "flip": 60.0,
      "flipSrc": "gamma",
      "call": 67,
      "put": 33,
      "callOI": 495045,
      "putOI": 169483,
      "callVol": 10054,
      "putVol": 8046,
      "dte": 37,
      "exp": "2026-08-21",
      "price": 52.2,
      "flow": "CALL HEAVY",
      "flowCls": "go"
    },
    {
      "t": "BMY",
      "gex": 7.4,
      "gexProxy": false,
      "flip": 40.0,
      "flipSrc": "gamma",
      "call": 71,
      "put": 29,
      "callOI": 45680,
      "putOI": 12143,
      "callVol": 1116,
      "putVol": 741,
      "dte": 37,
      "exp": "2026-08-21",
      "price": 58.34,
      "flow": "CALL HEAVY",
      "flowCls": "go"
    },
    {
      "t": "UNP",
      "gex": 7.3,
      "gexProxy": false,
      "flip": 275.0,
      "flipSrc": "gamma",
      "call": 55,
      "put": 45,
      "callOI": 10373,
      "putOI": 6324,
      "callVol": 113,
      "putVol": 137,
      "dte": 37,
      "exp": "2026-08-21",
      "price": 288.75,
      "flow": "CALL HEAVY",
      "flowCls": "go"
    },
    {
      "t": "XLP",
      "gex": 7.2,
      "gexProxy": false,
      "flip": 73.0,
      "flipSrc": "gamma",
      "call": 54,
      "put": 46,
      "callOI": 17090,
      "putOI": 7369,
      "callVol": 317,
      "putVol": 742,
      "dte": 37,
      "exp": "2026-08-21",
      "price": 83.84,
      "flow": "CALL HEAVY",
      "flowCls": "go"
    },
    {
      "t": "MRVL",
      "gex": 7.1,
      "gexProxy": false,
      "flip": 240.0,
      "flipSrc": "gamma",
      "call": 54,
      "put": 46,
      "callOI": 112586,
      "putOI": 84759,
      "callVol": 8441,
      "putVol": 8530,
      "dte": 37,
      "exp": "2026-08-21",
      "price": 207.83,
      "flow": "CALL HEAVY",
      "flowCls": "go"
    },
    {
      "t": "BLK",
      "gex": 6.9,
      "gexProxy": false,
      "flip": 1080.0,
      "flipSrc": "gamma",
      "call": 58,
      "put": 42,
      "callOI": 2402,
      "putOI": 1968,
      "callVol": 314,
      "putVol": 191,
      "dte": 37,
      "exp": "2026-08-21",
      "price": 1087.13,
      "flow": "CALL HEAVY",
      "flowCls": "go"
    },
    {
      "t": "AVGO",
      "gex": 6.8,
      "gexProxy": false,
      "flip": 480.0,
      "flipSrc": "gamma",
      "call": 58,
      "put": 42,
      "callOI": 102638,
      "putOI": 105096,
      "callVol": 5819,
      "putVol": 2390,
      "dte": 37,
      "exp": "2026-08-21",
      "price": 394.42,
      "flow": "CALL HEAVY",
      "flowCls": "go"
    },
    {
      "t": "DIS",
      "gex": 6.7,
      "gexProxy": false,
      "flip": 105.0,
      "flipSrc": "gamma",
      "call": 70,
      "put": 30,
      "callOI": 55338,
      "putOI": 31097,
      "callVol": 2459,
      "putVol": 680,
      "dte": 37,
      "exp": "2026-08-21",
      "price": 97.27,
      "flow": "CALL HEAVY",
      "flowCls": "go"
    },
    {
      "t": "CVS",
      "gex": 6.5,
      "gexProxy": false,
      "flip": 80.0,
      "flipSrc": "gamma",
      "call": 65,
      "put": 35,
      "callOI": 31078,
      "putOI": 19243,
      "callVol": 1832,
      "putVol": 791,
      "dte": 37,
      "exp": "2026-08-21",
      "price": 106.27,
      "flow": "CALL HEAVY",
      "flowCls": "go"
    },
    {
      "t": "SNOW",
      "gex": 6.5,
      "gexProxy": false,
      "flip": 140.0,
      "flipSrc": "gamma",
      "call": 62,
      "put": 38,
      "callOI": 29078,
      "putOI": 18590,
      "callVol": 771,
      "putVol": 460,
      "dte": 37,
      "exp": "2026-08-21",
      "price": 270.14,
      "flow": "CALL HEAVY",
      "flowCls": "go"
    },
    {
      "t": "HD",
      "gex": 6.5,
      "gexProxy": false,
      "flip": 365.0,
      "flipSrc": "gamma",
      "call": 59,
      "put": 41,
      "callOI": 18424,
      "putOI": 13262,
      "callVol": 597,
      "putVol": 386,
      "dte": 37,
      "exp": "2026-08-21",
      "price": 342.68,
      "flow": "CALL HEAVY",
      "flowCls": "go"
    },
    {
      "t": "VIX",
      "gex": 5.7,
      "gexProxy": false,
      "flip": 35.0,
      "flipSrc": "gamma",
      "call": 80,
      "put": 20,
      "callOI": 3209264,
      "putOI": 940652,
      "callVol": 134775,
      "putVol": 24038,
      "dte": 35,
      "exp": "2026-08-19",
      "price": 15.81,
      "flow": "CALL HEAVY",
      "flowCls": "go"
    },
    {
      "t": "PLTR",
      "gex": 5.7,
      "gexProxy": false,
      "flip": 70.0,
      "flipSrc": "gamma",
      "call": 65,
      "put": 35,
      "callOI": 204146,
      "putOI": 131511,
      "callVol": 14650,
      "putVol": 6028,
      "dte": 37,
      "exp": "2026-08-21",
      "price": 133.67,
      "flow": "CALL HEAVY",
      "flowCls": "go"
    },
    {
      "t": "NBIS",
      "gex": 5.5,
      "gexProxy": false,
      "flip": 250.0,
      "flipSrc": "gamma",
      "call": 62,
      "put": 38,
      "callOI": 76009,
      "putOI": 51981,
      "callVol": 6174,
      "putVol": 3050,
      "dte": 37,
      "exp": "2026-08-21",
      "price": 198.19,
      "flow": "CALL HEAVY",
      "flowCls": "go"
    },
    {
      "t": "NET",
      "gex": 5.5,
      "gexProxy": false,
      "flip": 250.0,
      "flipSrc": "gamma",
      "call": 63,
      "put": 37,
      "callOI": 23726,
      "putOI": 17363,
      "callVol": 824,
      "putVol": 332,
      "dte": 37,
      "exp": "2026-08-21",
      "price": 274.19,
      "flow": "CALL HEAVY",
      "flowCls": "go"
    },
    {
      "t": "MRK",
      "gex": 5.2,
      "gexProxy": false,
      "flip": 125.0,
      "flipSrc": "gamma",
      "call": 60,
      "put": 40,
      "callOI": 21191,
      "putOI": 9885,
      "callVol": 1127,
      "putVol": 1279,
      "dte": 37,
      "exp": "2026-08-21",
      "price": 123.38,
      "flow": "CALL HEAVY",
      "flowCls": "go"
    },
    {
      "t": "MS",
      "gex": 4.9,
      "gexProxy": false,
      "flip": 230.0,
      "flipSrc": "gamma",
      "call": 64,
      "put": 36,
      "callOI": 13921,
      "putOI": 13416,
      "callVol": 4921,
      "putVol": 1018,
      "dte": 37,
      "exp": "2026-08-21",
      "price": 229.6,
      "flow": "CALL HEAVY",
      "flowCls": "go"
    },
    {
      "t": "INTC",
      "gex": 4.7,
      "gexProxy": false,
      "flip": 140.0,
      "flipSrc": "gamma",
      "call": 66,
      "put": 34,
      "callOI": 264874,
      "putOI": 211296,
      "callVol": 36107,
      "putVol": 8838,
      "dte": 37,
      "exp": "2026-08-21",
      "price": 101.83,
      "flow": "CALL HEAVY",
      "flowCls": "go"
    },
    {
      "t": "CVX",
      "gex": 4.7,
      "gexProxy": false,
      "flip": 185.0,
      "flipSrc": "gamma",
      "call": 53,
      "put": 47,
      "callOI": 28947,
      "putOI": 20891,
      "callVol": 460,
      "putVol": 556,
      "dte": 37,
      "exp": "2026-08-21",
      "price": 180.15,
      "flow": "CALL HEAVY",
      "flowCls": "go"
    },
    {
      "t": "DVN",
      "gex": 4.4,
      "gexProxy": false,
      "flip": 27.5,
      "flipSrc": "gamma",
      "call": 89,
      "put": 11,
      "callOI": 92068,
      "putOI": 14119,
      "callVol": 3344,
      "putVol": 301,
      "dte": 37,
      "exp": "2026-08-21",
      "price": 42.61,
      "flow": "CALL HEAVY",
      "flowCls": "go"
    },
    {
      "t": "DHR",
      "gex": 4.4,
      "gexProxy": false,
      "flip": 200.0,
      "flipSrc": "gamma",
      "call": 58,
      "put": 42,
      "callOI": 7903,
      "putOI": 2769,
      "callVol": 18,
      "putVol": 34,
      "dte": 37,
      "exp": "2026-08-21",
      "price": 200.66,
      "flow": "CALL HEAVY",
      "flowCls": "go"
    },
    {
      "t": "WMB",
      "gex": 4.3,
      "gexProxy": false,
      "flip": 75.0,
      "flipSrc": "gamma",
      "call": 70,
      "put": 30,
      "callOI": 20537,
      "putOI": 7265,
      "callVol": 177,
      "putVol": 98,
      "dte": 37,
      "exp": "2026-08-21",
      "price": 74.94,
      "flow": "CALL HEAVY",
      "flowCls": "go"
    },
    {
      "t": "VTI",
      "gex": 4.3,
      "gexProxy": false,
      "flip": 305.0,
      "flipSrc": "gamma",
      "call": 67,
      "put": 33,
      "callOI": 2271,
      "putOI": 1118,
      "callVol": 110,
      "putVol": 51,
      "dte": 37,
      "exp": "2026-08-21",
      "price": 372.23,
      "flow": "CALL HEAVY",
      "flowCls": "go"
    },
    {
      "t": "SPOT",
      "gex": 4.2,
      "gexProxy": false,
      "flip": 460.0,
      "flipSrc": "gamma",
      "call": 60,
      "put": 40,
      "callOI": 15090,
      "putOI": 12323,
      "callVol": 274,
      "putVol": 126,
      "dte": 37,
      "exp": "2026-08-21",
      "price": 485.78,
      "flow": "CALL HEAVY",
      "flowCls": "go"
    },
    {
      "t": "UBER",
      "gex": 3.9,
      "gexProxy": false,
      "flip": 80.0,
      "flipSrc": "gamma",
      "call": 63,
      "put": 37,
      "callOI": 75435,
      "putOI": 56451,
      "callVol": 5493,
      "putVol": 2294,
      "dte": 37,
      "exp": "2026-08-21",
      "price": 72.92,
      "flow": "CALL HEAVY",
      "flowCls": "go"
    },
    {
      "t": "MMM",
      "gex": 3.6,
      "gexProxy": false,
      "flip": 110.0,
      "flipSrc": "gamma",
      "call": 76,
      "put": 24,
      "callOI": 11972,
      "putOI": 5725,
      "callVol": 2873,
      "putVol": 362,
      "dte": 37,
      "exp": "2026-08-21",
      "price": 160.55,
      "flow": "CALL HEAVY",
      "flowCls": "go"
    },
    {
      "t": "SOFI",
      "gex": 3.4,
      "gexProxy": false,
      "flip": 19.0,
      "flipSrc": "gamma",
      "call": 73,
      "put": 27,
      "callOI": 242094,
      "putOI": 84549,
      "callVol": 14875,
      "putVol": 6116,
      "dte": 37,
      "exp": "2026-08-21",
      "price": 18.11,
      "flow": "CALL HEAVY",
      "flowCls": "go"
    },
    {
      "t": "SCHW",
      "gex": 3.4,
      "gexProxy": false,
      "flip": 100.0,
      "flipSrc": "gamma",
      "call": 68,
      "put": 32,
      "callOI": 15894,
      "putOI": 14962,
      "callVol": 1316,
      "putVol": 103,
      "dte": 37,
      "exp": "2026-08-21",
      "price": 102.97,
      "flow": "CALL HEAVY",
      "flowCls": "go"
    },
    {
      "t": "XLV",
      "gex": 3.3,
      "gexProxy": false,
      "flip": 168.0,
      "flipSrc": "gamma",
      "call": 70,
      "put": 30,
      "callOI": 20157,
      "putOI": 16038,
      "callVol": 1524,
      "putVol": 133,
      "dte": 37,
      "exp": "2026-08-21",
      "price": 158.6,
      "flow": "CALL HEAVY",
      "flowCls": "go"
    },
    {
      "t": "AXP",
      "gex": 3.3,
      "gexProxy": false,
      "flip": 360.0,
      "flipSrc": "gamma",
      "call": 50,
      "put": 50,
      "callOI": 5525,
      "putOI": 5382,
      "callVol": 642,
      "putVol": 684,
      "dte": 37,
      "exp": "2026-08-21",
      "price": 360.58,
      "flow": "CALL HEAVY",
      "flowCls": "go"
    },
    {
      "t": "SMCI",
      "gex": 3.1,
      "gexProxy": false,
      "flip": 30.0,
      "flipSrc": "gamma",
      "call": 80,
      "put": 20,
      "callOI": 191956,
      "putOI": 57066,
      "callVol": 10260,
      "putVol": 2008,
      "dte": 37,
      "exp": "2026-08-21",
      "price": 27.11,
      "flow": "CALL HEAVY",
      "flowCls": "go"
    },
    {
      "t": "CSCO",
      "gex": 3.1,
      "gexProxy": false,
      "flip": 130.0,
      "flipSrc": "gamma",
      "call": 74,
      "put": 26,
      "callOI": 49317,
      "putOI": 23210,
      "callVol": 7672,
      "putVol": 1738,
      "dte": 37,
      "exp": "2026-08-21",
      "price": 112.29,
      "flow": "CALL HEAVY",
      "flowCls": "go"
    },
    {
      "t": "MDB",
      "gex": 3.0,
      "gexProxy": false,
      "flip": 140.0,
      "flipSrc": "gamma",
      "call": 56,
      "put": 44,
      "callOI": 11836,
      "putOI": 6940,
      "callVol": 435,
      "putVol": 530,
      "dte": 37,
      "exp": "2026-08-21",
      "price": 331.74,
      "flow": "CALL HEAVY",
      "flowCls": "go"
    },
    {
      "t": "MPC",
      "gex": 3.0,
      "gexProxy": false,
      "flip": 200.0,
      "flipSrc": "gamma",
      "call": 74,
      "put": 26,
      "callOI": 4907,
      "putOI": 2319,
      "callVol": 481,
      "putVol": 103,
      "dte": 37,
      "exp": "2026-08-21",
      "price": 297.48,
      "flow": "CALL HEAVY",
      "flowCls": "go"
    },
    {
      "t": "TGT",
      "gex": 2.9,
      "gexProxy": false,
      "flip": 130.0,
      "flipSrc": "gamma",
      "call": 69,
      "put": 31,
      "callOI": 16604,
      "putOI": 11380,
      "callVol": 1977,
      "putVol": 417,
      "dte": 37,
      "exp": "2026-08-21",
      "price": 138.06,
      "flow": "CALL HEAVY",
      "flowCls": "go"
    },
    {
      "t": "NKE",
      "gex": 2.8,
      "gexProxy": false,
      "flip": 47.5,
      "flipSrc": "gamma",
      "call": 73,
      "put": 27,
      "callOI": 94158,
      "putOI": 49356,
      "callVol": 7871,
      "putVol": 1475,
      "dte": 37,
      "exp": "2026-08-21",
      "price": 42.81,
      "flow": "CALL HEAVY",
      "flowCls": "go"
    },
    {
      "t": "CI",
      "gex": 2.8,
      "gexProxy": false,
      "flip": 220.0,
      "flipSrc": "gamma",
      "call": 68,
      "put": 32,
      "callOI": 3611,
      "putOI": 1412,
      "callVol": 32,
      "putVol": 20,
      "dte": 37,
      "exp": "2026-08-21",
      "price": 300.69,
      "flow": "CALL HEAVY",
      "flowCls": "go"
    },
    {
      "t": "AMGN",
      "gex": 2.7,
      "gexProxy": false,
      "flip": 310.0,
      "flipSrc": "gamma",
      "call": 62,
      "put": 38,
      "callOI": 7662,
      "putOI": 6383,
      "callVol": 531,
      "putVol": 209,
      "dte": 37,
      "exp": "2026-08-21",
      "price": 358.11,
      "flow": "CALL HEAVY",
      "flowCls": "go"
    },
    {
      "t": "DKNG",
      "gex": 2.6,
      "gexProxy": false,
      "flip": 27.5,
      "flipSrc": "gamma",
      "call": 64,
      "put": 36,
      "callOI": 93211,
      "putOI": 30246,
      "callVol": 738,
      "putVol": 879,
      "dte": 37,
      "exp": "2026-08-21",
      "price": 25.4,
      "flow": "CALL HEAVY",
      "flowCls": "go"
    },
    {
      "t": "MDT",
      "gex": 2.6,
      "gexProxy": false,
      "flip": 85.0,
      "flipSrc": "gamma",
      "call": 68,
      "put": 32,
      "callOI": 19520,
      "putOI": 12173,
      "callVol": 1987,
      "putVol": 556,
      "dte": 37,
      "exp": "2026-08-21",
      "price": 80.91,
      "flow": "CALL HEAVY",
      "flowCls": "go"
    },
    {
      "t": "DDOG",
      "gex": 2.6,
      "gexProxy": false,
      "flip": 150.0,
      "flipSrc": "gamma",
      "call": 71,
      "put": 29,
      "callOI": 16928,
      "putOI": 10920,
      "callVol": 2471,
      "putVol": 383,
      "dte": 37,
      "exp": "2026-08-21",
      "price": 264.16,
      "flow": "CALL HEAVY",
      "flowCls": "go"
    },
    {
      "t": "MELI",
      "gex": 2.6,
      "gexProxy": false,
      "flip": 1940.0,
      "flipSrc": "gamma",
      "call": 50,
      "put": 50,
      "callOI": 2842,
      "putOI": 3085,
      "callVol": 189,
      "putVol": 173,
      "dte": 37,
      "exp": "2026-08-21",
      "price": 1842.35,
      "flow": "CALL HEAVY",
      "flowCls": "go"
    },
    {
      "t": "UAL",
      "gex": 2.5,
      "gexProxy": false,
      "flip": 110.0,
      "flipSrc": "gamma",
      "call": 55,
      "put": 45,
      "callOI": 22509,
      "putOI": 12824,
      "callVol": 942,
      "putVol": 1289,
      "dte": 37,
      "exp": "2026-08-21",
      "price": 121.08,
      "flow": "CALL HEAVY",
      "flowCls": "go"
    },
    {
      "t": "TWLO",
      "gex": 2.5,
      "gexProxy": false,
      "flip": 115.0,
      "flipSrc": "gamma",
      "call": 81,
      "put": 19,
      "callOI": 10136,
      "putOI": 2630,
      "callVol": 101,
      "putVol": 20,
      "dte": 37,
      "exp": "2026-08-21",
      "price": 212.63,
      "flow": "CALL HEAVY",
      "flowCls": "go"
    },
    {
      "t": "ABNB",
      "gex": 2.5,
      "gexProxy": false,
      "flip": 145.0,
      "flipSrc": "gamma",
      "call": 75,
      "put": 25,
      "callOI": 8903,
      "putOI": 3639,
      "callVol": 606,
      "putVol": 140,
      "dte": 37,
      "exp": "2026-08-21",
      "price": 148.16,
      "flow": "CALL HEAVY",
      "flowCls": "go"
    },
    {
      "t": "ANET",
      "gex": 2.4,
      "gexProxy": false,
      "flip": 190.0,
      "flipSrc": "gamma",
      "call": 59,
      "put": 41,
      "callOI": 21855,
      "putOI": 15079,
      "callVol": 1181,
      "putVol": 801,
      "dte": 37,
      "exp": "2026-08-21",
      "price": 171.5,
      "flow": "CALL HEAVY",
      "flowCls": "go"
    },
    {
      "t": "COIN",
      "gex": 2.3,
      "gexProxy": false,
      "flip": 200.0,
      "flipSrc": "gamma",
      "call": 65,
      "put": 35,
      "callOI": 62311,
      "putOI": 52569,
      "callVol": 4460,
      "putVol": 1053,
      "dte": 37,
      "exp": "2026-08-21",
      "price": 165.28,
      "flow": "CALL HEAVY",
      "flowCls": "go"
    },
    {
      "t": "SBUX",
      "gex": 2.3,
      "gexProxy": false,
      "flip": 110.0,
      "flipSrc": "gamma",
      "call": 50,
      "put": 50,
      "callOI": 16114,
      "putOI": 10508,
      "callVol": 317,
      "putVol": 647,
      "dte": 37,
      "exp": "2026-08-21",
      "price": 106.17,
      "flow": "CALL HEAVY",
      "flowCls": "go"
    },
    {
      "t": "HIMS",
      "gex": 2.1,
      "gexProxy": false,
      "flip": 28.0,
      "flipSrc": "gamma",
      "call": 60,
      "put": 40,
      "callOI": 85116,
      "putOI": 45709,
      "callVol": 3646,
      "putVol": 3318,
      "dte": 37,
      "exp": "2026-08-21",
      "price": 36.82,
      "flow": "CALL HEAVY",
      "flowCls": "go"
    },
    {
      "t": "BX",
      "gex": 2.1,
      "gexProxy": false,
      "flip": 135.0,
      "flipSrc": "gamma",
      "call": 51,
      "put": 49,
      "callOI": 16857,
      "putOI": 19314,
      "callVol": 1654,
      "putVol": 1277,
      "dte": 37,
      "exp": "2026-08-21",
      "price": 127.14,
      "flow": "CALL HEAVY",
      "flowCls": "go"
    },
    {
      "t": "PSX",
      "gex": 1.9,
      "gexProxy": false,
      "flip": 180.0,
      "flipSrc": "gamma",
      "call": 66,
      "put": 34,
      "callOI": 7672,
      "putOI": 5460,
      "callVol": 312,
      "putVol": 94,
      "dte": 37,
      "exp": "2026-08-21",
      "price": 195.28,
      "flow": "CALL HEAVY",
      "flowCls": "go"
    },
    {
      "t": "ADP",
      "gex": 1.9,
      "gexProxy": false,
      "flip": 250.0,
      "flipSrc": "gamma",
      "call": 67,
      "put": 33,
      "callOI": 3830,
      "putOI": 3539,
      "callVol": 177,
      "putVol": 21,
      "dte": 37,
      "exp": "2026-08-21",
      "price": 245.94,
      "flow": "CALL HEAVY",
      "flowCls": "go"
    },
    {
      "t": "SYK",
      "gex": 1.8,
      "gexProxy": false,
      "flip": 195.0,
      "flipSrc": "gamma",
      "call": 75,
      "put": 25,
      "callOI": 3252,
      "putOI": 701,
      "callVol": 51,
      "putVol": 29,
      "dte": 37,
      "exp": "2026-08-21",
      "price": 314.98,
      "flow": "CALL HEAVY",
      "flowCls": "go"
    },
    {
      "t": "JD",
      "gex": 1.7,
      "gexProxy": false,
      "flip": 22.0,
      "flipSrc": "gamma",
      "call": 62,
      "put": 38,
      "callOI": 29580,
      "putOI": 6690,
      "callVol": 1731,
      "putVol": 3745,
      "dte": 37,
      "exp": "2026-08-21",
      "price": 29.41,
      "flow": "CALL HEAVY",
      "flowCls": "go"
    },
    {
      "t": "DELL",
      "gex": 1.7,
      "gexProxy": false,
      "flip": 500.0,
      "flipSrc": "gamma",
      "call": 56,
      "put": 44,
      "callOI": 24875,
      "putOI": 24975,
      "callVol": 6626,
      "putVol": 3726,
      "dte": 37,
      "exp": "2026-08-21",
      "price": 404.89,
      "flow": "CALL HEAVY",
      "flowCls": "go"
    },
    {
      "t": "XLU",
      "gex": 1.6,
      "gexProxy": false,
      "flip": 42.0,
      "flipSrc": "gamma",
      "call": 59,
      "put": 41,
      "callOI": 17861,
      "putOI": 11917,
      "callVol": 628,
      "putVol": 466,
      "dte": 37,
      "exp": "2026-08-21",
      "price": 45.35,
      "flow": "CALL HEAVY",
      "flowCls": "go"
    },
    {
      "t": "NOW",
      "gex": 1.5,
      "gexProxy": false,
      "flip": 150.0,
      "flipSrc": "gamma",
      "call": 58,
      "put": 42,
      "callOI": 115685,
      "putOI": 99323,
      "callVol": 4273,
      "putVol": 2490,
      "dte": 37,
      "exp": "2026-08-21",
      "price": 104.73,
      "flow": "CALL HEAVY",
      "flowCls": "go"
    },
    {
      "t": "ZS",
      "gex": 1.5,
      "gexProxy": false,
      "flip": 165.0,
      "flipSrc": "gamma",
      "call": 61,
      "put": 39,
      "callOI": 25019,
      "putOI": 18537,
      "callVol": 1641,
      "putVol": 798,
      "dte": 37,
      "exp": "2026-08-21",
      "price": 147.75,
      "flow": "CALL HEAVY",
      "flowCls": "go"
    },
    {
      "t": "ICE",
      "gex": 1.5,
      "gexProxy": false,
      "flip": 140.0,
      "flipSrc": "gamma",
      "call": 82,
      "put": 18,
      "callOI": 4017,
      "putOI": 1036,
      "callVol": 91,
      "putVol": 14,
      "dte": 37,
      "exp": "2026-08-21",
      "price": 139.59,
      "flow": "CALL HEAVY",
      "flowCls": "go"
    },
    {
      "t": "COP",
      "gex": 1.4,
      "gexProxy": false,
      "flip": 120.0,
      "flipSrc": "gamma",
      "call": 73,
      "put": 27,
      "callOI": 22687,
      "putOI": 11482,
      "callVol": 311,
      "putVol": 63,
      "dte": 37,
      "exp": "2026-08-21",
      "price": 110.81,
      "flow": "CALL HEAVY",
      "flowCls": "go"
    },
    {
      "t": "TXN",
      "gex": 1.4,
      "gexProxy": false,
      "flip": 350.0,
      "flipSrc": "gamma",
      "call": 60,
      "put": 40,
      "callOI": 10504,
      "putOI": 10311,
      "callVol": 975,
      "putVol": 343,
      "dte": 37,
      "exp": "2026-08-21",
      "price": 299.97,
      "flow": "CALL HEAVY",
      "flowCls": "go"
    },
    {
      "t": "XLRE",
      "gex": 1.4,
      "gexProxy": false,
      "flip": 45.0,
      "flipSrc": "gamma",
      "call": 67,
      "put": 33,
      "callOI": 5668,
      "putOI": 2906,
      "callVol": 540,
      "putVol": 238,
      "dte": 37,
      "exp": "2026-08-21",
      "price": 44.65,
      "flow": "CALL HEAVY",
      "flowCls": "go"
    },
    {
      "t": "MCO",
      "gex": 1.4,
      "gexProxy": false,
      "flip": 300.0,
      "flipSrc": "gamma",
      "call": 67,
      "put": 33,
      "callOI": 2720,
      "putOI": 3249,
      "callVol": 1864,
      "putVol": 16,
      "dte": 37,
      "exp": "2026-08-21",
      "price": 505.13,
      "flow": "CALL HEAVY",
      "flowCls": "go"
    },
    {
      "t": "OXY",
      "gex": 1.3,
      "gexProxy": false,
      "flip": 60.0,
      "flipSrc": "gamma",
      "call": 72,
      "put": 28,
      "callOI": 64768,
      "putOI": 30093,
      "callVol": 1547,
      "putVol": 458,
      "dte": 37,
      "exp": "2026-08-21",
      "price": 53.36,
      "flow": "CALL HEAVY",
      "flowCls": "go"
    },
    {
      "t": "SHOP",
      "gex": 1.3,
      "gexProxy": false,
      "flip": 135.0,
      "flipSrc": "gamma",
      "call": 55,
      "put": 45,
      "callOI": 17898,
      "putOI": 17015,
      "callVol": 704,
      "putVol": 464,
      "dte": 37,
      "exp": "2026-08-21",
      "price": 124.47,
      "flow": "CALL HEAVY",
      "flowCls": "go"
    },
    {
      "t": "CSX",
      "gex": 1.3,
      "gexProxy": false,
      "flip": 35.0,
      "flipSrc": "gamma",
      "call": 62,
      "put": 38,
      "callOI": 13228,
      "putOI": 8545,
      "callVol": 684,
      "putVol": 380,
      "dte": 37,
      "exp": "2026-08-21",
      "price": 49.34,
      "flow": "CALL HEAVY",
      "flowCls": "go"
    },
    {
      "t": "ETSY",
      "gex": 1.3,
      "gexProxy": false,
      "flip": 80.0,
      "flipSrc": "gamma",
      "call": 66,
      "put": 34,
      "callOI": 11837,
      "putOI": 6548,
      "callVol": 152,
      "putVol": 72,
      "dte": 37,
      "exp": "2026-08-21",
      "price": 85.43,
      "flow": "CALL HEAVY",
      "flowCls": "go"
    },
    {
      "t": "HPE",
      "gex": 1.2,
      "gexProxy": false,
      "flip": 23.0,
      "flipSrc": "gamma",
      "call": 59,
      "put": 41,
      "callOI": 61105,
      "putOI": 30554,
      "callVol": 1404,
      "putVol": 1525,
      "dte": 37,
      "exp": "2026-08-21",
      "price": 47.04,
      "flow": "CALL HEAVY",
      "flowCls": "go"
    },
    {
      "t": "ZM",
      "gex": 1.2,
      "gexProxy": false,
      "flip": 95.0,
      "flipSrc": "gamma",
      "call": 61,
      "put": 39,
      "callOI": 17988,
      "putOI": 9666,
      "callVol": 309,
      "putVol": 248,
      "dte": 37,
      "exp": "2026-08-21",
      "price": 92.24,
      "flow": "CALL HEAVY",
      "flowCls": "go"
    },
    {
      "t": "FROG",
      "gex": 1.2,
      "gexProxy": false,
      "flip": 80.0,
      "flipSrc": "gamma",
      "call": 74,
      "put": 26,
      "callOI": 10787,
      "putOI": 715,
      "callVol": 125,
      "putVol": 164,
      "dte": 37,
      "exp": "2026-08-21",
      "price": 90.87,
      "flow": "CALL HEAVY",
      "flowCls": "go"
    },
    {
      "t": "GD",
      "gex": 1.2,
      "gexProxy": false,
      "flip": 370.0,
      "flipSrc": "gamma",
      "call": 53,
      "put": 47,
      "callOI": 1668,
      "putOI": 1493,
      "callVol": 20,
      "putVol": 18,
      "dte": 37,
      "exp": "2026-08-21",
      "price": 367.65,
      "flow": "CALL HEAVY",
      "flowCls": "go"
    },
    {
      "t": "ADBE",
      "gex": 1.1,
      "gexProxy": false,
      "flip": 280.0,
      "flipSrc": "gamma",
      "call": 63,
      "put": 37,
      "callOI": 58787,
      "putOI": 27303,
      "callVol": 1275,
      "putVol": 1031,
      "dte": 37,
      "exp": "2026-08-21",
      "price": 223.65,
      "flow": "CALL HEAVY",
      "flowCls": "go"
    },
    {
      "t": "SLB",
      "gex": 1.1,
      "gexProxy": false,
      "flip": 52.5,
      "flipSrc": "gamma",
      "call": 67,
      "put": 33,
      "callOI": 55783,
      "putOI": 20831,
      "callVol": 1247,
      "putVol": 898,
      "dte": 37,
      "exp": "2026-08-21",
      "price": 47.43,
      "flow": "CALL HEAVY",
      "flowCls": "go"
    },
    {
      "t": "CMG",
      "gex": 1.1,
      "gexProxy": false,
      "flip": 32.5,
      "flipSrc": "gamma",
      "call": 72,
      "put": 28,
      "callOI": 19109,
      "putOI": 6038,
      "callVol": 1411,
      "putVol": 771,
      "dte": 37,
      "exp": "2026-08-21",
      "price": 36.01,
      "flow": "CALL HEAVY",
      "flowCls": "go"
    },
    {
      "t": "BKNG",
      "gex": 1.1,
      "gexProxy": false,
      "flip": 190.0,
      "flipSrc": "gamma",
      "call": 56,
      "put": 44,
      "callOI": 7642,
      "putOI": 7224,
      "callVol": 606,
      "putVol": 355,
      "dte": 37,
      "exp": "2026-08-21",
      "price": 180.73,
      "flow": "CALL HEAVY",
      "flowCls": "go"
    },
    {
      "t": "DUK",
      "gex": 1.1,
      "gexProxy": false,
      "flip": 135.0,
      "flipSrc": "gamma",
      "call": 59,
      "put": 41,
      "callOI": 6653,
      "putOI": 3237,
      "callVol": 100,
      "putVol": 111,
      "dte": 37,
      "exp": "2026-08-21",
      "price": 124.94,
      "flow": "CALL HEAVY",
      "flowCls": "go"
    },
    {
      "t": "INTU",
      "gex": 1.1,
      "gexProxy": false,
      "flip": 170.0,
      "flipSrc": "gamma",
      "call": 62,
      "put": 38,
      "callOI": 6395,
      "putOI": 4310,
      "callVol": 314,
      "putVol": 163,
      "dte": 37,
      "exp": "2026-08-21",
      "price": 279.25,
      "flow": "CALL HEAVY",
      "flowCls": "go"
    },
    {
      "t": "TMO",
      "gex": 1.1,
      "gexProxy": false,
      "flip": 530.0,
      "flipSrc": "gamma",
      "call": 64,
      "put": 36,
      "callOI": 1082,
      "putOI": 667,
      "callVol": 63,
      "putVol": 32,
      "dte": 37,
      "exp": "2026-08-21",
      "price": 538.34,
      "flow": "CALL HEAVY",
      "flowCls": "go"
    },
    {
      "t": "BIDU",
      "gex": 1.0,
      "gexProxy": false,
      "flip": 135.0,
      "flipSrc": "gamma",
      "call": 78,
      "put": 22,
      "callOI": 21998,
      "putOI": 11000,
      "callVol": 967,
      "putVol": 50,
      "dte": 37,
      "exp": "2026-08-21",
      "price": 112.25,
      "flow": "CALL HEAVY",
      "flowCls": "go"
    },
    {
      "t": "OKTA",
      "gex": 1.0,
      "gexProxy": false,
      "flip": 72.5,
      "flipSrc": "gamma",
      "call": 70,
      "put": 30,
      "callOI": 12507,
      "putOI": 8244,
      "callVol": 1134,
      "putVol": 179,
      "dte": 37,
      "exp": "2026-08-21",
      "price": 149.72,
      "flow": "CALL HEAVY",
      "flowCls": "go"
    },
    {
      "t": "OKE",
      "gex": 1.0,
      "gexProxy": false,
      "flip": 90.0,
      "flipSrc": "gamma",
      "call": 58,
      "put": 42,
      "callOI": 6166,
      "putOI": 3376,
      "callVol": 127,
      "putVol": 141,
      "dte": 37,
      "exp": "2026-08-21",
      "price": 90.86,
      "flow": "CALL HEAVY",
      "flowCls": "go"
    },
    {
      "t": "EBAY",
      "gex": 1.0,
      "gexProxy": false,
      "flip": 75.0,
      "flipSrc": "gamma",
      "call": 80,
      "put": 20,
      "callOI": 6120,
      "putOI": 1895,
      "callVol": 89,
      "putVol": 14,
      "dte": 37,
      "exp": "2026-08-21",
      "price": 112.99,
      "flow": "CALL HEAVY",
      "flowCls": "go"
    },
    {
      "t": "CME",
      "gex": 1.0,
      "gexProxy": false,
      "flip": 250.0,
      "flipSrc": "gamma",
      "call": 61,
      "put": 39,
      "callOI": 5264,
      "putOI": 4122,
      "callVol": 211,
      "putVol": 99,
      "dte": 37,
      "exp": "2026-08-21",
      "price": 245.52,
      "flow": "CALL HEAVY",
      "flowCls": "go"
    },
    {
      "t": "RUN",
      "gex": 0.9,
      "gexProxy": false,
      "flip": 6.0,
      "flipSrc": "gamma",
      "call": 90,
      "put": 10,
      "callOI": 80995,
      "putOI": 13339,
      "callVol": 3310,
      "putVol": 189,
      "dte": 37,
      "exp": "2026-08-21",
      "price": 12.79,
      "flow": "CALL HEAVY",
      "flowCls": "go"
    },
    {
      "t": "KKR",
      "gex": 0.9,
      "gexProxy": false,
      "flip": 105.0,
      "flipSrc": "gamma",
      "call": 54,
      "put": 46,
      "callOI": 10624,
      "putOI": 10883,
      "callVol": 477,
      "putVol": 295,
      "dte": 37,
      "exp": "2026-08-21",
      "price": 100.5,
      "flow": "CALL HEAVY",
      "flowCls": "go"
    },
    {
      "t": "XLC",
      "gex": 0.9,
      "gexProxy": false,
      "flip": 114.0,
      "flipSrc": "gamma",
      "call": 57,
      "put": 43,
      "callOI": 2309,
      "putOI": 2419,
      "callVol": 158,
      "putVol": 68,
      "dte": 37,
      "exp": "2026-08-21",
      "price": 113.21,
      "flow": "CALL HEAVY",
      "flowCls": "go"
    },
    {
      "t": "XPEV",
      "gex": 0.8,
      "gexProxy": false,
      "flip": 9.0,
      "flipSrc": "gamma",
      "call": 90,
      "put": 10,
      "callOI": 47494,
      "putOI": 4301,
      "callVol": 1572,
      "putVol": 242,
      "dte": 37,
      "exp": "2026-08-21",
      "price": 13.96,
      "flow": "CALL HEAVY",
      "flowCls": "go"
    },
    {
      "t": "GNRC",
      "gex": 0.8,
      "gexProxy": false,
      "flip": 95.0,
      "flipSrc": "gamma",
      "call": 77,
      "put": 23,
      "callOI": 5647,
      "putOI": 2038,
      "callVol": 724,
      "putVol": 143,
      "dte": 37,
      "exp": "2026-08-21",
      "price": 223.65,
      "flow": "CALL HEAVY",
      "flowCls": "go"
    },
    {
      "t": "FANG",
      "gex": 0.7,
      "gexProxy": false,
      "flip": 190.0,
      "flipSrc": "gamma",
      "call": 79,
      "put": 21,
      "callOI": 2114,
      "putOI": 525,
      "callVol": 83,
      "putVol": 23,
      "dte": 37,
      "exp": "2026-08-21",
      "price": 189.03,
      "flow": "CALL HEAVY",
      "flowCls": "go"
    },
    {
      "t": "NIO",
      "gex": 0.6,
      "gexProxy": false,
      "flip": 5.0,
      "flipSrc": "gamma",
      "call": 76,
      "put": 24,
      "callOI": 229441,
      "putOI": 98393,
      "callVol": 7723,
      "putVol": 1345,
      "dte": 37,
      "exp": "2026-08-21",
      "price": 5.07,
      "flow": "CALL HEAVY",
      "flowCls": "go"
    },
    {
      "t": "PDD",
      "gex": 0.6,
      "gexProxy": false,
      "flip": 105.0,
      "flipSrc": "gamma",
      "call": 72,
      "put": 28,
      "callOI": 62404,
      "putOI": 38675,
      "callVol": 2138,
      "putVol": 335,
      "dte": 37,
      "exp": "2026-08-21",
      "price": 86.43,
      "flow": "CALL HEAVY",
      "flowCls": "go"
    },
    {
      "t": "LYFT",
      "gex": 0.6,
      "gexProxy": false,
      "flip": 7.0,
      "flipSrc": "gamma",
      "call": 73,
      "put": 27,
      "callOI": 38450,
      "putOI": 20543,
      "callVol": 1110,
      "putVol": 194,
      "dte": 37,
      "exp": "2026-08-21",
      "price": 16.17,
      "flow": "CALL HEAVY",
      "flowCls": "go"
    },
    {
      "t": "RBLX",
      "gex": 0.6,
      "gexProxy": false,
      "flip": 60.0,
      "flipSrc": "gamma",
      "call": 54,
      "put": 46,
      "callOI": 17170,
      "putOI": 12609,
      "callVol": 611,
      "putVol": 669,
      "dte": 37,
      "exp": "2026-08-21",
      "price": 56.59,
      "flow": "CALL HEAVY",
      "flowCls": "go"
    },
    {
      "t": "DOCN",
      "gex": 0.6,
      "gexProxy": false,
      "flip": 45.0,
      "flipSrc": "gamma",
      "call": 75,
      "put": 25,
      "callOI": 14310,
      "putOI": 6195,
      "callVol": 711,
      "putVol": 150,
      "dte": 37,
      "exp": "2026-08-21",
      "price": 117.65,
      "flow": "CALL HEAVY",
      "flowCls": "go"
    },
    {
      "t": "BILL",
      "gex": 0.6,
      "gexProxy": false,
      "flip": 45.0,
      "flipSrc": "gamma",
      "call": 80,
      "put": 20,
      "callOI": 12661,
      "putOI": 5874,
      "callVol": 536,
      "putVol": 18,
      "dte": 37,
      "exp": "2026-08-21",
      "price": 44.23,
      "flow": "CALL HEAVY",
      "flowCls": "go"
    },
    {
      "t": "HON",
      "gex": 0.6,
      "gexProxy": true,
      "flip": 220.0,
      "flipSrc": "oi-atm",
      "call": 74,
      "put": 26,
      "callOI": 10131,
      "putOI": 7462,
      "callVol": 437,
      "putVol": 13,
      "dte": 37,
      "exp": "2026-08-21",
      "price": 222.23,
      "flow": "CALL HEAVY",
      "flowCls": "go"
    },
    {
      "t": "HUM",
      "gex": 0.6,
      "gexProxy": false,
      "flip": 210.0,
      "flipSrc": "gamma",
      "call": 63,
      "put": 37,
      "callOI": 7246,
      "putOI": 5728,
      "callVol": 68,
      "putVol": 25,
      "dte": 37,
      "exp": "2026-08-21",
      "price": 409.31,
      "flow": "CALL HEAVY",
      "flowCls": "go"
    },
    {
      "t": "STT",
      "gex": 0.6,
      "gexProxy": false,
      "flip": 135.0,
      "flipSrc": "gamma",
      "call": 78,
      "put": 22,
      "callOI": 2083,
      "putOI": 869,
      "callVol": 311,
      "putVol": 39,
      "dte": 37,
      "exp": "2026-08-21",
      "price": 184.84,
      "flow": "CALL HEAVY",
      "flowCls": "go"
    },
    {
      "t": "PINS",
      "gex": 0.5,
      "gexProxy": false,
      "flip": 25.0,
      "flipSrc": "gamma",
      "call": 57,
      "put": 43,
      "callOI": 29185,
      "putOI": 26275,
      "callVol": 549,
      "putVol": 309,
      "dte": 37,
      "exp": "2026-08-21",
      "price": 23.27,
      "flow": "CALL HEAVY",
      "flowCls": "go"
    },
    {
      "t": "TEAM",
      "gex": 0.5,
      "gexProxy": false,
      "flip": 95.0,
      "flipSrc": "gamma",
      "call": 74,
      "put": 26,
      "callOI": 8527,
      "putOI": 4055,
      "callVol": 395,
      "putVol": 84,
      "dte": 37,
      "exp": "2026-08-21",
      "price": 91.45,
      "flow": "CALL HEAVY",
      "flowCls": "go"
    },
    {
      "t": "KMI",
      "gex": 0.5,
      "gexProxy": false,
      "flip": 29.0,
      "flipSrc": "gamma",
      "call": 75,
      "put": 25,
      "callOI": 7932,
      "putOI": 3604,
      "callVol": 1396,
      "putVol": 284,
      "dte": 37,
      "exp": "2026-08-21",
      "price": 32.2,
      "flow": "CALL HEAVY",
      "flowCls": "go"
    },
    {
      "t": "RIVN",
      "gex": 0.4,
      "gexProxy": false,
      "flip": 9.0,
      "flipSrc": "gamma",
      "call": 66,
      "put": 34,
      "callOI": 30463,
      "putOI": 21216,
      "callVol": 5480,
      "putVol": 1601,
      "dte": 37,
      "exp": "2026-08-21",
      "price": 17.97,
      "flow": "CALL HEAVY",
      "flowCls": "go"
    },
    {
      "t": "SQQQ",
      "gex": 0.4,
      "gexProxy": false,
      "flip": 30.0,
      "flipSrc": "gamma",
      "call": 76,
      "put": 24,
      "callOI": 11198,
      "putOI": 2927,
      "callVol": 1491,
      "putVol": 605,
      "dte": 37,
      "exp": "2026-08-21",
      "price": 39.02,
      "flow": "CALL HEAVY",
      "flowCls": "go"
    },
    {
      "t": "NTNX",
      "gex": 0.4,
      "gexProxy": false,
      "flip": 47.5,
      "flipSrc": "gamma",
      "call": 85,
      "put": 15,
      "callOI": 4881,
      "putOI": 886,
      "callVol": 21,
      "putVol": 0,
      "dte": 37,
      "exp": "2026-08-21",
      "price": 54.08,
      "flow": "CALL HEAVY",
      "flowCls": "go"
    },
    {
      "t": "UNG",
      "gex": 0.3,
      "gexProxy": false,
      "flip": 8.0,
      "flipSrc": "gamma",
      "call": 87,
      "put": 13,
      "callOI": 34351,
      "putOI": 5471,
      "callVol": 1691,
      "putVol": 236,
      "dte": 37,
      "exp": "2026-08-21",
      "price": 10.56,
      "flow": "CALL HEAVY",
      "flowCls": "go"
    },
    {
      "t": "VST",
      "gex": 0.3,
      "gexProxy": false,
      "flip": 210.0,
      "flipSrc": "gamma",
      "call": 56,
      "put": 44,
      "callOI": 18327,
      "putOI": 25986,
      "callVol": 1799,
      "putVol": 470,
      "dte": 37,
      "exp": "2026-08-21",
      "price": 159.4,
      "flow": "CALL HEAVY",
      "flowCls": "go"
    },
    {
      "t": "BITO",
      "gex": 0.3,
      "gexProxy": false,
      "flip": 8.0,
      "flipSrc": "gamma",
      "call": 88,
      "put": 12,
      "callOI": 14653,
      "putOI": 1749,
      "callVol": 458,
      "putVol": 69,
      "dte": 37,
      "exp": "2026-08-21",
      "price": 8.83,
      "flow": "CALL HEAVY",
      "flowCls": "go"
    },
    {
      "t": "S",
      "gex": 0.3,
      "gexProxy": false,
      "flip": 12.0,
      "flipSrc": "gamma",
      "call": 87,
      "put": 13,
      "callOI": 10524,
      "putOI": 1679,
      "callVol": 501,
      "putVol": 60,
      "dte": 37,
      "exp": "2026-08-21",
      "price": 19.97,
      "flow": "CALL HEAVY",
      "flowCls": "go"
    },
    {
      "t": "DASH",
      "gex": 0.3,
      "gexProxy": false,
      "flip": 220.0,
      "flipSrc": "gamma",
      "call": 50,
      "put": 50,
      "callOI": 7318,
      "putOI": 9643,
      "callVol": 51,
      "putVol": 32,
      "dte": 37,
      "exp": "2026-08-21",
      "price": 192.07,
      "flow": "CALL HEAVY",
      "flowCls": "go"
    },
    {
      "t": "ALK",
      "gex": 0.3,
      "gexProxy": false,
      "flip": 52.5,
      "flipSrc": "gamma",
      "call": 73,
      "put": 27,
      "callOI": 6607,
      "putOI": 1086,
      "callVol": 84,
      "putVol": 74,
      "dte": 37,
      "exp": "2026-08-21",
      "price": 48.11,
      "flow": "CALL HEAVY",
      "flowCls": "go"
    },
    {
      "t": "LUV",
      "gex": 0.3,
      "gexProxy": false,
      "flip": 50.0,
      "flipSrc": "gamma",
      "call": 69,
      "put": 31,
      "callOI": 4369,
      "putOI": 1738,
      "callVol": 404,
      "putVol": 223,
      "dte": 37,
      "exp": "2026-08-21",
      "price": 49.29,
      "flow": "CALL HEAVY",
      "flowCls": "go"
    },
    {
      "t": "BNTX",
      "gex": 0.3,
      "gexProxy": false,
      "flip": 90.0,
      "flipSrc": "gamma",
      "call": 65,
      "put": 35,
      "callOI": 3437,
      "putOI": 1620,
      "callVol": 171,
      "putVol": 115,
      "dte": 37,
      "exp": "2026-08-21",
      "price": 90.9,
      "flow": "CALL HEAVY",
      "flowCls": "go"
    },
    {
      "t": "TTD",
      "gex": 0.2,
      "gexProxy": false,
      "flip": 20.0,
      "flipSrc": "gamma",
      "call": 79,
      "put": 21,
      "callOI": 14916,
      "putOI": 5404,
      "callVol": 1006,
      "putVol": 122,
      "dte": 37,
      "exp": "2026-08-21",
      "price": 19.16,
      "flow": "CALL HEAVY",
      "flowCls": "go"
    },
    {
      "t": "RBRK",
      "gex": 0.2,
      "gexProxy": false,
      "flip": 90.0,
      "flipSrc": "gamma",
      "call": 70,
      "put": 30,
      "callOI": 3511,
      "putOI": 2045,
      "callVol": 264,
      "putVol": 60,
      "dte": 37,
      "exp": "2026-08-21",
      "price": 80.43,
      "flow": "CALL HEAVY",
      "flowCls": "go"
    },
    {
      "t": "DOCU",
      "gex": 0.2,
      "gexProxy": false,
      "flip": 47.5,
      "flipSrc": "gamma",
      "call": 64,
      "put": 36,
      "callOI": 2541,
      "putOI": 1610,
      "callVol": 617,
      "putVol": 284,
      "dte": 37,
      "exp": "2026-08-21",
      "price": 50.33,
      "flow": "CALL HEAVY",
      "flowCls": "go"
    },
    {
      "t": "HUBS",
      "gex": 0.2,
      "gexProxy": false,
      "flip": 190.0,
      "flipSrc": "gamma",
      "call": 72,
      "put": 28,
      "callOI": 1428,
      "putOI": 801,
      "callVol": 128,
      "putVol": 26,
      "dte": 37,
      "exp": "2026-08-21",
      "price": 211.56,
      "flow": "CALL HEAVY",
      "flowCls": "go"
    },
    {
      "t": "ASTS",
      "gex": 0.1,
      "gexProxy": false,
      "flip": 150.0,
      "flipSrc": "gamma",
      "call": 71,
      "put": 29,
      "callOI": 91193,
      "putOI": 55570,
      "callVol": 11108,
      "putVol": 1985,
      "dte": 37,
      "exp": "2026-08-21",
      "price": 67.41,
      "flow": "CALL HEAVY",
      "flowCls": "go"
    },
    {
      "t": "ACHR",
      "gex": 0.1,
      "gexProxy": false,
      "flip": 5.0,
      "flipSrc": "gamma",
      "call": 87,
      "put": 13,
      "callOI": 26693,
      "putOI": 4546,
      "callVol": 1507,
      "putVol": 154,
      "dte": 37,
      "exp": "2026-08-21",
      "price": 4.83,
      "flow": "CALL HEAVY",
      "flowCls": "go"
    },
    {
      "t": "SOUN",
      "gex": 0.1,
      "gexProxy": false,
      "flip": 7.0,
      "flipSrc": "gamma",
      "call": 68,
      "put": 32,
      "callOI": 25332,
      "putOI": 6651,
      "callVol": 51947,
      "putVol": 47233,
      "dte": 37,
      "exp": "2026-08-21",
      "price": 6.54,
      "flow": "CALL HEAVY",
      "flowCls": "go"
    },
    {
      "t": "SNAP",
      "gex": 0.1,
      "gexProxy": false,
      "flip": 3.0,
      "flipSrc": "gamma",
      "call": 71,
      "put": 29,
      "callOI": 21321,
      "putOI": 8921,
      "callVol": 839,
      "putVol": 335,
      "dte": 37,
      "exp": "2026-08-21",
      "price": 4.79,
      "flow": "CALL HEAVY",
      "flowCls": "go"
    },
    {
      "t": "ABT",
      "gex": 0.1,
      "gexProxy": false,
      "flip": 105.0,
      "flipSrc": "gamma",
      "call": 63,
      "put": 37,
      "callOI": 20139,
      "putOI": 15602,
      "callVol": 1174,
      "putVol": 430,
      "dte": 37,
      "exp": "2026-08-21",
      "price": 88.95,
      "flow": "CALL HEAVY",
      "flowCls": "go"
    },
    {
      "t": "DAL",
      "gex": 0.1,
      "gexProxy": false,
      "flip": 105.0,
      "flipSrc": "gamma",
      "call": 54,
      "put": 46,
      "callOI": 12239,
      "putOI": 11870,
      "callVol": 627,
      "putVol": 447,
      "dte": 37,
      "exp": "2026-08-21",
      "price": 85.94,
      "flow": "CALL HEAVY",
      "flowCls": "go"
    },
    {
      "t": "UPST",
      "gex": 0.1,
      "gexProxy": false,
      "flip": 42.5,
      "flipSrc": "gamma",
      "call": 66,
      "put": 34,
      "callOI": 6289,
      "putOI": 4254,
      "callVol": 299,
      "putVol": 97,
      "dte": 37,
      "exp": "2026-08-21",
      "price": 31.9,
      "flow": "CALL HEAVY",
      "flowCls": "go"
    },
    {
      "t": "ROKU",
      "gex": 0.1,
      "gexProxy": false,
      "flip": 115.0,
      "flipSrc": "gamma",
      "call": 74,
      "put": 26,
      "callOI": 703,
      "putOI": 512,
      "callVol": 439,
      "putVol": 3,
      "dte": 37,
      "exp": "2026-08-21",
      "price": 142.88,
      "flow": "CALL HEAVY",
      "flowCls": "go"
    },
    {
      "t": "LCID",
      "gex": 0.0,
      "gexProxy": true,
      "flip": 6.0,
      "flipSrc": "oi-atm",
      "call": 60,
      "put": 40,
      "callOI": 121608,
      "putOI": 114921,
      "callVol": 10217,
      "putVol": 3513,
      "dte": 37,
      "exp": "2026-08-21",
      "price": 5.66,
      "flow": "CALL HEAVY",
      "flowCls": "go"
    },
    {
      "t": "RKLB",
      "gex": 0.0,
      "gexProxy": false,
      "flip": 175.0,
      "flipSrc": "gamma",
      "call": 71,
      "put": 29,
      "callOI": 60721,
      "putOI": 31012,
      "callVol": 4326,
      "putVol": 1124,
      "dte": 37,
      "exp": "2026-08-21",
      "price": 76.8,
      "flow": "CALL HEAVY",
      "flowCls": "go"
    },
    {
      "t": "HPQ",
      "gex": 0.0,
      "gexProxy": false,
      "flip": 30.0,
      "flipSrc": "gamma",
      "call": 58,
      "put": 42,
      "callOI": 41698,
      "putOI": 36400,
      "callVol": 1002,
      "putVol": 540,
      "dte": 37,
      "exp": "2026-08-21",
      "price": 23.59,
      "flow": "CALL HEAVY",
      "flowCls": "go"
    },
    {
      "t": "JOBY",
      "gex": -0.0,
      "gexProxy": false,
      "flip": 3.0,
      "flipSrc": "gamma",
      "call": 73,
      "put": 27,
      "callOI": 35816,
      "putOI": 22382,
      "callVol": 1061,
      "putVol": 137,
      "dte": 37,
      "exp": "2026-08-21",
      "price": 7.79,
      "flow": "CALL HEAVY",
      "flowCls": "go"
    },
    {
      "t": "BBAI",
      "gex": 0.0,
      "gexProxy": false,
      "flip": 5.0,
      "flipSrc": "gamma",
      "call": 71,
      "put": 29,
      "callOI": 15088,
      "putOI": 7757,
      "callVol": 677,
      "putVol": 194,
      "dte": 37,
      "exp": "2026-08-21",
      "price": 3.17,
      "flow": "CALL HEAVY",
      "flowCls": "go"
    },
    {
      "t": "MCD",
      "gex": -0.0,
      "gexProxy": false,
      "flip": 195.0,
      "flipSrc": "gamma",
      "call": 56,
      "put": 44,
      "callOI": 14404,
      "putOI": 11234,
      "callVol": 1840,
      "putVol": 1413,
      "dte": 37,
      "exp": "2026-08-21",
      "price": 266.84,
      "flow": "CALL HEAVY",
      "flowCls": "go"
    },
    {
      "t": "UVXY",
      "gex": 0.0,
      "gexProxy": false,
      "flip": 15.0,
      "flipSrc": "gamma",
      "call": 74,
      "put": 26,
      "callOI": 14354,
      "putOI": 8804,
      "callVol": 933,
      "putVol": 85,
      "dte": 37,
      "exp": "2026-08-21",
      "price": 22.93,
      "flow": "CALL HEAVY",
      "flowCls": "go"
    },
    {
      "t": "CRSP",
      "gex": -0.0,
      "gexProxy": false,
      "flip": 50.0,
      "flipSrc": "oi-atm",
      "call": 55,
      "put": 45,
      "callOI": 3452,
      "putOI": 2576,
      "callVol": 138,
      "putVol": 126,
      "dte": 37,
      "exp": "2026-08-21",
      "price": 51.0,
      "flow": "CALL HEAVY",
      "flowCls": "go"
    },
    {
      "t": "NVAX",
      "gex": -0.0,
      "gexProxy": false,
      "flip": 7.0,
      "flipSrc": "gamma",
      "call": 57,
      "put": 43,
      "callOI": 3239,
      "putOI": 4268,
      "callVol": 43,
      "putVol": 13,
      "dte": 37,
      "exp": "2026-08-21",
      "price": 8.33,
      "flow": "CALL HEAVY",
      "flowCls": "go"
    },
    {
      "t": "BAM",
      "gex": 0.0,
      "gexProxy": false,
      "flip": 52.5,
      "flipSrc": "gamma",
      "call": 57,
      "put": 43,
      "callOI": 2570,
      "putOI": 3460,
      "callVol": 169,
      "putVol": 47,
      "dte": 37,
      "exp": "2026-08-21",
      "price": 49.22,
      "flow": "CALL HEAVY",
      "flowCls": "go"
    },
    {
      "t": "PENN",
      "gex": 0.0,
      "gexProxy": false,
      "flip": 20.0,
      "flipSrc": "gamma",
      "call": 79,
      "put": 21,
      "callOI": 1781,
      "putOI": 927,
      "callVol": 146,
      "putVol": 1,
      "dte": 37,
      "exp": "2026-08-21",
      "price": 20.88,
      "flow": "CALL HEAVY",
      "flowCls": "go"
    },
    {
      "t": "PAYC",
      "gex": 0.0,
      "gexProxy": false,
      "flip": 165.0,
      "flipSrc": "gamma",
      "call": 62,
      "put": 38,
      "callOI": 1553,
      "putOI": 2273,
      "callVol": 80,
      "putVol": 6,
      "dte": 37,
      "exp": "2026-08-21",
      "price": 144.34,
      "flow": "CALL HEAVY",
      "flowCls": "go"
    },
    {
      "t": "ALNY",
      "gex": 0.0,
      "gexProxy": false,
      "flip": 280.0,
      "flipSrc": "gamma",
      "call": 70,
      "put": 30,
      "callOI": 1516,
      "putOI": 1150,
      "callVol": 76,
      "putVol": 9,
      "dte": 37,
      "exp": "2026-08-21",
      "price": 279.54,
      "flow": "CALL HEAVY",
      "flowCls": "go"
    },
    {
      "t": "PLAB",
      "gex": 0.0,
      "gexProxy": false,
      "flip": 20.0,
      "flipSrc": "gamma",
      "call": 54,
      "put": 46,
      "callOI": 1494,
      "putOI": 877,
      "callVol": 74,
      "putVol": 107,
      "dte": 37,
      "exp": "2026-08-21",
      "price": 29.47,
      "flow": "CALL HEAVY",
      "flowCls": "go"
    },
    {
      "t": "BIIB",
      "gex": 0.0,
      "gexProxy": false,
      "flip": 170.0,
      "flipSrc": "gamma",
      "call": 72,
      "put": 28,
      "callOI": 1454,
      "putOI": 835,
      "callVol": 58,
      "putVol": 10,
      "dte": 37,
      "exp": "2026-08-21",
      "price": 196.35,
      "flow": "CALL HEAVY",
      "flowCls": "go"
    },
    {
      "t": "ETHE",
      "gex": 0.0,
      "gexProxy": false,
      "flip": 16.0,
      "flipSrc": "oi-atm",
      "call": 96,
      "put": 4,
      "callOI": 1004,
      "putOI": 24,
      "callVol": 56,
      "putVol": 4,
      "dte": 37,
      "exp": "2026-08-21",
      "price": 15.55,
      "flow": "CALL HEAVY",
      "flowCls": "go"
    },
    {
      "t": "ISRG",
      "gex": -0.1,
      "gexProxy": false,
      "flip": 400.0,
      "flipSrc": "oi-atm",
      "call": 63,
      "put": 37,
      "callOI": 7424,
      "putOI": 5255,
      "callVol": 702,
      "putVol": 302,
      "dte": 37,
      "exp": "2026-08-21",
      "price": 389.79,
      "flow": "CALL HEAVY",
      "flowCls": "go"
    },
    {
      "t": "SPXS",
      "gex": -0.1,
      "gexProxy": false,
      "flip": 22.0,
      "flipSrc": "gamma",
      "call": 53,
      "put": 47,
      "callOI": 3569,
      "putOI": 4716,
      "callVol": 178,
      "putVol": 84,
      "dte": 37,
      "exp": "2026-08-21",
      "price": 25.78,
      "flow": "CALL HEAVY",
      "flowCls": "go"
    },
    {
      "t": "ELV",
      "gex": -0.2,
      "gexProxy": false,
      "flip": 360.0,
      "flipSrc": "oi-atm",
      "call": 63,
      "put": 37,
      "callOI": 1479,
      "putOI": 1310,
      "callVol": 963,
      "putVol": 290,
      "dte": 37,
      "exp": "2026-08-21",
      "price": 388.58,
      "flow": "CALL HEAVY",
      "flowCls": "go"
    },
    {
      "t": "SEDG",
      "gex": -0.3,
      "gexProxy": false,
      "flip": 55.0,
      "flipSrc": "oi-atm",
      "call": 56,
      "put": 44,
      "callOI": 17886,
      "putOI": 21937,
      "callVol": 296,
      "putVol": 111,
      "dte": 37,
      "exp": "2026-08-21",
      "price": 54.5,
      "flow": "CALL HEAVY",
      "flowCls": "go"
    },
    {
      "t": "NOC",
      "gex": -0.4,
      "gexProxy": false,
      "flip": 550.0,
      "flipSrc": "oi-atm",
      "call": 58,
      "put": 42,
      "callOI": 2626,
      "putOI": 2013,
      "callVol": 34,
      "putVol": 23,
      "dte": 37,
      "exp": "2026-08-21",
      "price": 530.52,
      "flow": "CALL HEAVY",
      "flowCls": "go"
    },
    {
      "t": "BA",
      "gex": -0.8,
      "gexProxy": false,
      "flip": 220.0,
      "flipSrc": "oi-atm",
      "call": 66,
      "put": 34,
      "callOI": 82249,
      "putOI": 76619,
      "callVol": 3402,
      "putVol": 534,
      "dte": 37,
      "exp": "2026-08-21",
      "price": 219.29,
      "flow": "CALL HEAVY",
      "flowCls": "go"
    },
    {
      "t": "FTNT",
      "gex": -1.0,
      "gexProxy": false,
      "flip": 80.0,
      "flipSrc": "gamma",
      "call": 52,
      "put": 48,
      "callOI": 8530,
      "putOI": 17172,
      "callVol": 533,
      "putVol": 136,
      "dte": 37,
      "exp": "2026-08-21",
      "price": 164.04,
      "flow": "CALL HEAVY",
      "flowCls": "go"
    },
    {
      "t": "LRCX",
      "gex": -1.1,
      "gexProxy": false,
      "flip": 360.0,
      "flipSrc": "oi-atm",
      "call": 53,
      "put": 47,
      "callOI": 41417,
      "putOI": 47063,
      "callVol": 1421,
      "putVol": 867,
      "dte": 37,
      "exp": "2026-08-21",
      "price": 332.1,
      "flow": "CALL HEAVY",
      "flowCls": "go"
    },
    {
      "t": "FSLR",
      "gex": -1.1,
      "gexProxy": false,
      "flip": 240.0,
      "flipSrc": "oi-atm",
      "call": 56,
      "put": 44,
      "callOI": 19494,
      "putOI": 14633,
      "callVol": 822,
      "putVol": 698,
      "dte": 37,
      "exp": "2026-08-21",
      "price": 224.68,
      "flow": "CALL HEAVY",
      "flowCls": "go"
    },
    {
      "t": "XLK",
      "gex": -2.0,
      "gexProxy": false,
      "flip": 105.0,
      "flipSrc": "gamma",
      "call": 57,
      "put": 43,
      "callOI": 28106,
      "putOI": 36119,
      "callVol": 1912,
      "putVol": 606,
      "dte": 37,
      "exp": "2026-08-21",
      "price": 181.06,
      "flow": "CALL HEAVY",
      "flowCls": "go"
    },
    {
      "t": "CEG",
      "gex": -2.4,
      "gexProxy": false,
      "flip": 270.0,
      "flipSrc": "oi-atm",
      "call": 53,
      "put": 47,
      "callOI": 16680,
      "putOI": 18466,
      "callVol": 648,
      "putVol": 385,
      "dte": 37,
      "exp": "2026-08-21",
      "price": 257.36,
      "flow": "CALL HEAVY",
      "flowCls": "go"
    },
    {
      "t": "KLAC",
      "gex": -2.6,
      "gexProxy": false,
      "flip": 234.0,
      "flipSrc": "oi-atm",
      "call": 52,
      "put": 48,
      "callOI": 23712,
      "putOI": 46609,
      "callVol": 5790,
      "putVol": 1434,
      "dte": 37,
      "exp": "2026-08-21",
      "price": 223.75,
      "flow": "CALL HEAVY",
      "flowCls": "go"
    },
    {
      "t": "QCOM",
      "gex": -3.1,
      "gexProxy": false,
      "flip": 175.0,
      "flipSrc": "oi-atm",
      "call": 57,
      "put": 43,
      "callOI": 53625,
      "putOI": 50876,
      "callVol": 2488,
      "putVol": 1202,
      "dte": 37,
      "exp": "2026-08-21",
      "price": 177.9,
      "flow": "CALL HEAVY",
      "flowCls": "go"
    },
    {
      "t": "LOW",
      "gex": -3.1,
      "gexProxy": false,
      "flip": 195.0,
      "flipSrc": "oi-atm",
      "call": 52,
      "put": 48,
      "callOI": 3827,
      "putOI": 8395,
      "callVol": 241,
      "putVol": 45,
      "dte": 37,
      "exp": "2026-08-21",
      "price": 210.59,
      "flow": "CALL HEAVY",
      "flowCls": "go"
    },
    {
      "t": "IBM",
      "gex": -3.2,
      "gexProxy": false,
      "flip": 220.0,
      "flipSrc": "oi-atm",
      "call": 56,
      "put": 44,
      "callOI": 55971,
      "putOI": 39545,
      "callVol": 12802,
      "putVol": 11852,
      "dte": 37,
      "exp": "2026-08-21",
      "price": 213.77,
      "flow": "CALL HEAVY",
      "flowCls": "go"
    },
    {
      "t": "ORCL",
      "gex": -5.0,
      "gexProxy": false,
      "flip": 130.0,
      "flipSrc": "oi-atm",
      "call": 66,
      "put": 34,
      "callOI": 185399,
      "putOI": 124783,
      "callVol": 22548,
      "putVol": 7092,
      "dte": 37,
      "exp": "2026-08-21",
      "price": 132.7,
      "flow": "CALL HEAVY",
      "flowCls": "go"
    },
    {
      "t": "PFE",
      "gex": -7.0,
      "gexProxy": false,
      "flip": 23.0,
      "flipSrc": "oi-atm",
      "call": 58,
      "put": 42,
      "callOI": 109664,
      "putOI": 160371,
      "callVol": 13210,
      "putVol": 2559,
      "dte": 37,
      "exp": "2026-08-21",
      "price": 24.68,
      "flow": "CALL HEAVY",
      "flowCls": "go"
    },
    {
      "t": "COST",
      "gex": -9.8,
      "gexProxy": false,
      "flip": 970.0,
      "flipSrc": "oi-atm",
      "call": 56,
      "put": 44,
      "callOI": 17565,
      "putOI": 17645,
      "callVol": 2361,
      "putVol": 1237,
      "dte": 37,
      "exp": "2026-08-21",
      "price": 921.59,
      "flow": "CALL HEAVY",
      "flowCls": "go"
    },
    {
      "t": "NFLX",
      "gex": -10.0,
      "gexProxy": false,
      "flip": 73.0,
      "flipSrc": "oi-atm",
      "call": 64,
      "put": 36,
      "callOI": 410946,
      "putOI": 269452,
      "callVol": 12911,
      "putVol": 5451,
      "dte": 37,
      "exp": "2026-08-21",
      "price": 73.76,
      "flow": "CALL HEAVY",
      "flowCls": "go"
    },
    {
      "t": "TSM",
      "gex": -15.1,
      "gexProxy": false,
      "flip": 400.0,
      "flipSrc": "oi-atm",
      "call": 56,
      "put": 44,
      "callOI": 101958,
      "putOI": 137918,
      "callVol": 10577,
      "putVol": 3258,
      "dte": 37,
      "exp": "2026-08-21",
      "price": 420.38,
      "flow": "CALL HEAVY",
      "flowCls": "go"
    },
    {
      "t": "GLD",
      "gex": -23.7,
      "gexProxy": false,
      "flip": 400.0,
      "flipSrc": "oi-atm",
      "call": 61,
      "put": 39,
      "callOI": 165029,
      "putOI": 98564,
      "callVol": 4890,
      "putVol": 3397,
      "dte": 37,
      "exp": "2026-08-21",
      "price": 372.91,
      "flow": "CALL HEAVY",
      "flowCls": "go"
    },
    {
      "t": "LQD",
      "gex": -108.8,
      "gexProxy": false,
      "flip": 110.0,
      "flipSrc": "oi-atm",
      "call": 62,
      "put": 38,
      "callOI": 174330,
      "putOI": 229880,
      "callVol": 1363,
      "putVol": 155,
      "dte": 37,
      "exp": "2026-08-21",
      "price": 107.61,
      "flow": "CALL HEAVY",
      "flowCls": "go"
    },
    {
      "t": "TLT",
      "gex": -109.9,
      "gexProxy": false,
      "flip": 85.0,
      "flipSrc": "oi-atm",
      "call": 58,
      "put": 42,
      "callOI": 378207,
      "putOI": 292132,
      "callVol": 33937,
      "putVol": 20812,
      "dte": 37,
      "exp": "2026-08-21",
      "price": 84.3,
      "flow": "CALL HEAVY",
      "flowCls": "go"
    },
    {
      "t": "XLF",
      "gex": 26.4,
      "gexProxy": false,
      "flip": 54.0,
      "flipSrc": "gamma",
      "call": 47,
      "put": 53,
      "callOI": 241752,
      "putOI": 313598,
      "callVol": 10968,
      "putVol": 10318,
      "dte": 37,
      "exp": "2026-08-21",
      "price": 56.58,
      "flow": "PUT HEAVY",
      "flowCls": "nogo"
    },
    {
      "t": "DIA",
      "gex": 23.5,
      "gexProxy": false,
      "flip": 530.0,
      "flipSrc": "gamma",
      "call": 46,
      "put": 54,
      "callOI": 13183,
      "putOI": 12232,
      "callVol": 832,
      "putVol": 1442,
      "dte": 37,
      "exp": "2026-08-21",
      "price": 525.97,
      "flow": "PUT HEAVY",
      "flowCls": "nogo"
    },
    {
      "t": "ASML",
      "gex": 8.6,
      "gexProxy": false,
      "flip": 1980.0,
      "flipSrc": "gamma",
      "call": 46,
      "put": 54,
      "callOI": 11587,
      "putOI": 12505,
      "callVol": 819,
      "putVol": 1026,
      "dte": 37,
      "exp": "2026-08-21",
      "price": 1790.98,
      "flow": "PUT HEAVY",
      "flowCls": "nogo"
    },
    {
      "t": "PANW",
      "gex": 4.9,
      "gexProxy": false,
      "flip": 185.0,
      "flipSrc": "gamma",
      "call": 47,
      "put": 53,
      "callOI": 27406,
      "putOI": 26466,
      "callVol": 740,
      "putVol": 1107,
      "dte": 37,
      "exp": "2026-08-21",
      "price": 356.08,
      "flow": "PUT HEAVY",
      "flowCls": "nogo"
    },
    {
      "t": "WFC",
      "gex": 2.6,
      "gexProxy": false,
      "flip": 95.0,
      "flipSrc": "gamma",
      "call": 48,
      "put": 52,
      "callOI": 46576,
      "putOI": 52149,
      "callVol": 3662,
      "putVol": 3804,
      "dte": 37,
      "exp": "2026-08-21",
      "price": 86.93,
      "flow": "PUT HEAVY",
      "flowCls": "nogo"
    },
    {
      "t": "AMAT",
      "gex": 2.6,
      "gexProxy": false,
      "flip": 730.0,
      "flipSrc": "gamma",
      "call": 43,
      "put": 57,
      "callOI": 21737,
      "putOI": 29609,
      "callVol": 1281,
      "putVol": 1537,
      "dte": 37,
      "exp": "2026-08-21",
      "price": 578.01,
      "flow": "PUT HEAVY",
      "flowCls": "nogo"
    },
    {
      "t": "XLY",
      "gex": 2.5,
      "gexProxy": false,
      "flip": 104.0,
      "flipSrc": "gamma",
      "call": 43,
      "put": 57,
      "callOI": 7125,
      "putOI": 4296,
      "callVol": 85,
      "putVol": 497,
      "dte": 37,
      "exp": "2026-08-21",
      "price": 117.52,
      "flow": "PUT HEAVY",
      "flowCls": "nogo"
    },
    {
      "t": "PYPL",
      "gex": 2.3,
      "gexProxy": false,
      "flip": 50.0,
      "flipSrc": "gamma",
      "call": 46,
      "put": 54,
      "callOI": 23918,
      "putOI": 25947,
      "callVol": 13423,
      "putVol": 18321,
      "dte": 37,
      "exp": "2026-08-21",
      "price": 55.1,
      "flow": "PUT HEAVY",
      "flowCls": "nogo"
    },
    {
      "t": "SO",
      "gex": 1.4,
      "gexProxy": false,
      "flip": 97.5,
      "flipSrc": "gamma",
      "call": 38,
      "put": 62,
      "callOI": 8762,
      "putOI": 6692,
      "callVol": 19,
      "putVol": 169,
      "dte": 37,
      "exp": "2026-08-21",
      "price": 95.02,
      "flow": "PUT HEAVY",
      "flowCls": "nogo"
    },
    {
      "t": "RTX",
      "gex": 1.3,
      "gexProxy": false,
      "flip": 210.0,
      "flipSrc": "gamma",
      "call": 48,
      "put": 52,
      "callOI": 19017,
      "putOI": 20781,
      "callVol": 350,
      "putVol": 368,
      "dte": 37,
      "exp": "2026-08-21",
      "price": 195.27,
      "flow": "PUT HEAVY",
      "flowCls": "nogo"
    },
    {
      "t": "AFRM",
      "gex": 1.2,
      "gexProxy": false,
      "flip": 85.0,
      "flipSrc": "gamma",
      "call": 49,
      "put": 51,
      "callOI": 19121,
      "putOI": 17579,
      "callVol": 454,
      "putVol": 563,
      "dte": 37,
      "exp": "2026-08-21",
      "price": 82.08,
      "flow": "PUT HEAVY",
      "flowCls": "nogo"
    },
    {
      "t": "CRWV",
      "gex": 1.1,
      "gexProxy": false,
      "flip": 120.0,
      "flipSrc": "gamma",
      "call": 47,
      "put": 53,
      "callOI": 109909,
      "putOI": 67683,
      "callVol": 12677,
      "putVol": 37480,
      "dte": 37,
      "exp": "2026-08-21",
      "price": 78.4,
      "flow": "PUT HEAVY",
      "flowCls": "nogo"
    },
    {
      "t": "NEE",
      "gex": 1.0,
      "gexProxy": false,
      "flip": 92.5,
      "flipSrc": "gamma",
      "call": 45,
      "put": 55,
      "callOI": 7912,
      "putOI": 6916,
      "callVol": 291,
      "putVol": 568,
      "dte": 37,
      "exp": "2026-08-21",
      "price": 88.69,
      "flow": "PUT HEAVY",
      "flowCls": "nogo"
    },
    {
      "t": "SOXL",
      "gex": 0.8,
      "gexProxy": false,
      "flip": 81.0,
      "flipSrc": "gamma",
      "call": 37,
      "put": 63,
      "callOI": 59492,
      "putOI": 73686,
      "callVol": 3087,
      "putVol": 9944,
      "dte": 37,
      "exp": "2026-08-21",
      "price": 163.31,
      "flow": "PUT HEAVY",
      "flowCls": "nogo"
    },
    {
      "t": "DE",
      "gex": 0.4,
      "gexProxy": false,
      "flip": 670.0,
      "flipSrc": "gamma",
      "call": 47,
      "put": 53,
      "callOI": 1814,
      "putOI": 1390,
      "callVol": 43,
      "putVol": 92,
      "dte": 37,
      "exp": "2026-08-21",
      "price": 589.88,
      "flow": "PUT HEAVY",
      "flowCls": "nogo"
    },
    {
      "t": "HAL",
      "gex": 0.3,
      "gexProxy": false,
      "flip": 37.0,
      "flipSrc": "gamma",
      "call": 47,
      "put": 53,
      "callOI": 9368,
      "putOI": 5383,
      "callVol": 238,
      "putVol": 834,
      "dte": 37,
      "exp": "2026-08-21",
      "price": 35.02,
      "flow": "PUT HEAVY",
      "flowCls": "nogo"
    },
    {
      "t": "TROW",
      "gex": 0.3,
      "gexProxy": false,
      "flip": 115.0,
      "flipSrc": "gamma",
      "call": 39,
      "put": 61,
      "callOI": 975,
      "putOI": 521,
      "callVol": 55,
      "putVol": 4023,
      "dte": 37,
      "exp": "2026-08-21",
      "price": 118.17,
      "flow": "PUT HEAVY",
      "flowCls": "nogo"
    },
    {
      "t": "GE",
      "gex": 0.2,
      "gexProxy": false,
      "flip": 430.0,
      "flipSrc": "gamma",
      "call": 41,
      "put": 59,
      "callOI": 6847,
      "putOI": 8322,
      "callVol": 877,
      "putVol": 1599,
      "dte": 37,
      "exp": "2026-08-21",
      "price": 358.3,
      "flow": "PUT HEAVY",
      "flowCls": "nogo"
    },
    {
      "t": "SPGI",
      "gex": 0.2,
      "gexProxy": true,
      "flip": 450.0,
      "flipSrc": "oi-atm",
      "call": 43,
      "put": 57,
      "callOI": 2502,
      "putOI": 2081,
      "callVol": 47,
      "putVol": 140,
      "dte": 37,
      "exp": "2026-08-21",
      "price": 443.83,
      "flow": "PUT HEAVY",
      "flowCls": "nogo"
    },
    {
      "t": "APP",
      "gex": 0.1,
      "gexProxy": false,
      "flip": 760.0,
      "flipSrc": "gamma",
      "call": 48,
      "put": 52,
      "callOI": 16539,
      "putOI": 13244,
      "callVol": 414,
      "putVol": 715,
      "dte": 37,
      "exp": "2026-08-21",
      "price": 455.68,
      "flow": "PUT HEAVY",
      "flowCls": "nogo"
    },
    {
      "t": "EOG",
      "gex": 0.1,
      "gexProxy": false,
      "flip": 150.0,
      "flipSrc": "gamma",
      "call": 46,
      "put": 54,
      "callOI": 1995,
      "putOI": 2297,
      "callVol": 20,
      "putVol": 29,
      "dte": 37,
      "exp": "2026-08-21",
      "price": 136.48,
      "flow": "PUT HEAVY",
      "flowCls": "nogo"
    },
    {
      "t": "UPRO",
      "gex": 0.1,
      "gexProxy": false,
      "flip": 145.0,
      "flipSrc": "gamma",
      "call": 27,
      "put": 73,
      "callOI": 1667,
      "putOI": 2380,
      "callVol": 95,
      "putVol": 1341,
      "dte": 37,
      "exp": "2026-08-21",
      "price": 145.62,
      "flow": "PUT HEAVY",
      "flowCls": "nogo"
    },
    {
      "t": "UPRO",
      "gex": 0.1,
      "gexProxy": false,
      "flip": 145.0,
      "flipSrc": "gamma",
      "call": 27,
      "put": 73,
      "callOI": 1667,
      "putOI": 2380,
      "callVol": 95,
      "putVol": 1341,
      "dte": 37,
      "exp": "2026-08-21",
      "price": 145.62,
      "flow": "PUT HEAVY",
      "flowCls": "nogo"
    },
    {
      "t": "FDX",
      "gex": 0.0,
      "gexProxy": false,
      "flip": 380.0,
      "flipSrc": "gamma",
      "call": 46,
      "put": 54,
      "callOI": 2342,
      "putOI": 2301,
      "callVol": 67,
      "putVol": 99,
      "dte": 37,
      "exp": "2026-08-21",
      "price": 318.1,
      "flow": "PUT HEAVY",
      "flowCls": "nogo"
    },
    {
      "t": "EME",
      "gex": 0.0,
      "gexProxy": false,
      "flip": 860.0,
      "flipSrc": "gamma",
      "call": 48,
      "put": 52,
      "callOI": 342,
      "putOI": 368,
      "callVol": 6,
      "putVol": 8,
      "dte": 37,
      "exp": "2026-08-21",
      "price": 770.34,
      "flow": "PUT HEAVY",
      "flowCls": "nogo"
    },
    {
      "t": "TQQQ",
      "gex": -0.2,
      "gexProxy": false,
      "flip": 75.0,
      "flipSrc": "oi-atm",
      "call": 39,
      "put": 61,
      "callOI": 23745,
      "putOI": 31991,
      "callVol": 2012,
      "putVol": 3957,
      "dte": 37,
      "exp": "2026-08-21",
      "price": 74.29,
      "flow": "PUT HEAVY",
      "flowCls": "nogo"
    },
    {
      "t": "WDAY",
      "gex": -0.2,
      "gexProxy": false,
      "flip": 140.0,
      "flipSrc": "oi-atm",
      "call": 27,
      "put": 73,
      "callOI": 1695,
      "putOI": 2947,
      "callVol": 34,
      "putVol": 289,
      "dte": 37,
      "exp": "2026-08-21",
      "price": 141.54,
      "flow": "PUT HEAVY",
      "flowCls": "nogo"
    },
    {
      "t": "VRTX",
      "gex": -0.2,
      "gexProxy": false,
      "flip": 500.0,
      "flipSrc": "oi-atm",
      "call": 46,
      "put": 54,
      "callOI": 1529,
      "putOI": 1651,
      "callVol": 154,
      "putVol": 213,
      "dte": 37,
      "exp": "2026-08-21",
      "price": 478.1,
      "flow": "PUT HEAVY",
      "flowCls": "nogo"
    },
    {
      "t": "AAL",
      "gex": -0.3,
      "gexProxy": false,
      "flip": 15.0,
      "flipSrc": "oi-atm",
      "call": 40,
      "put": 60,
      "callOI": 80518,
      "putOI": 157572,
      "callVol": 2440,
      "putVol": 2424,
      "dte": 37,
      "exp": "2026-08-21",
      "price": 15.72,
      "flow": "PUT HEAVY",
      "flowCls": "nogo"
    },
    {
      "t": "FUTU",
      "gex": -0.3,
      "gexProxy": false,
      "flip": 92.45,
      "flipSrc": "oi-atm",
      "call": 42,
      "put": 58,
      "callOI": 7684,
      "putOI": 16640,
      "callVol": 360,
      "putVol": 258,
      "dte": 37,
      "exp": "2026-08-21",
      "price": 99.47,
      "flow": "PUT HEAVY",
      "flowCls": "nogo"
    },
    {
      "t": "NDAQ",
      "gex": -0.3,
      "gexProxy": false,
      "flip": 82.5,
      "flipSrc": "oi-atm",
      "call": 46,
      "put": 54,
      "callOI": 723,
      "putOI": 3554,
      "callVol": 95,
      "putVol": 10,
      "dte": 37,
      "exp": "2026-08-21",
      "price": 91.25,
      "flow": "PUT HEAVY",
      "flowCls": "nogo"
    },
    {
      "t": "LI",
      "gex": -0.6,
      "gexProxy": false,
      "flip": 9.0,
      "flipSrc": "gamma",
      "call": 23,
      "put": 77,
      "callOI": 5175,
      "putOI": 50910,
      "callVol": 207,
      "putVol": 274,
      "dte": 37,
      "exp": "2026-08-21",
      "price": 12.78,
      "flow": "PUT HEAVY",
      "flowCls": "nogo"
    },
    {
      "t": "ENPH",
      "gex": -0.7,
      "gexProxy": false,
      "flip": 40.0,
      "flipSrc": "oi-atm",
      "call": 43,
      "put": 57,
      "callOI": 28236,
      "putOI": 30540,
      "callVol": 602,
      "putVol": 1122,
      "dte": 37,
      "exp": "2026-08-21",
      "price": 44.05,
      "flow": "PUT HEAVY",
      "flowCls": "nogo"
    },
    {
      "t": "MRNA",
      "gex": -0.8,
      "gexProxy": false,
      "flip": 65.0,
      "flipSrc": "oi-atm",
      "call": 27,
      "put": 73,
      "callOI": 22031,
      "putOI": 46079,
      "callVol": 372,
      "putVol": 1618,
      "dte": 37,
      "exp": "2026-08-21",
      "price": 67.37,
      "flow": "PUT HEAVY",
      "flowCls": "nogo"
    },
    {
      "t": "LMT",
      "gex": -0.8,
      "gexProxy": false,
      "flip": 535.0,
      "flipSrc": "oi-atm",
      "call": 29,
      "put": 71,
      "callOI": 1983,
      "putOI": 3968,
      "callVol": 104,
      "putVol": 375,
      "dte": 37,
      "exp": "2026-08-21",
      "price": 514.49,
      "flow": "PUT HEAVY",
      "flowCls": "nogo"
    },
    {
      "t": "BSX",
      "gex": -1.0,
      "gexProxy": false,
      "flip": 35.0,
      "flipSrc": "gamma",
      "call": 49,
      "put": 51,
      "callOI": 56164,
      "putOI": 33187,
      "callVol": 360,
      "putVol": 889,
      "dte": 37,
      "exp": "2026-08-21",
      "price": 43.29,
      "flow": "PUT HEAVY",
      "flowCls": "nogo"
    },
    {
      "t": "ETN",
      "gex": -1.0,
      "gexProxy": false,
      "flip": 440.0,
      "flipSrc": "oi-atm",
      "call": 24,
      "put": 76,
      "callOI": 2853,
      "putOI": 5050,
      "callVol": 188,
      "putVol": 3568,
      "dte": 37,
      "exp": "2026-08-21",
      "price": 411.37,
      "flow": "PUT HEAVY",
      "flowCls": "nogo"
    },
    {
      "t": "ARM",
      "gex": -1.1,
      "gexProxy": false,
      "flip": 130.0,
      "flipSrc": "gamma",
      "call": 43,
      "put": 57,
      "callOI": 49822,
      "putOI": 64640,
      "callVol": 2320,
      "putVol": 3348,
      "dte": 37,
      "exp": "2026-08-21",
      "price": 274.26,
      "flow": "PUT HEAVY",
      "flowCls": "nogo"
    },
    {
      "t": "NSC",
      "gex": -1.2,
      "gexProxy": false,
      "flip": 300.0,
      "flipSrc": "oi-atm",
      "call": 26,
      "put": 74,
      "callOI": 1151,
      "putOI": 3343,
      "callVol": 10,
      "putVol": 8,
      "dte": 37,
      "exp": "2026-08-21",
      "price": 327.39,
      "flow": "PUT HEAVY",
      "flowCls": "nogo"
    },
    {
      "t": "REGN",
      "gex": -1.5,
      "gexProxy": false,
      "flip": 600.0,
      "flipSrc": "oi-atm",
      "call": 44,
      "put": 56,
      "callOI": 1576,
      "putOI": 2025,
      "callVol": 18,
      "putVol": 7,
      "dte": 37,
      "exp": "2026-08-21",
      "price": 661.86,
      "flow": "PUT HEAVY",
      "flowCls": "nogo"
    },
    {
      "t": "PWR",
      "gex": -4.3,
      "gexProxy": false,
      "flip": 340.0,
      "flipSrc": "gamma",
      "call": 26,
      "put": 74,
      "callOI": 2962,
      "putOI": 8388,
      "callVol": 66,
      "putVol": 178,
      "dte": 37,
      "exp": "2026-08-21",
      "price": 652.36,
      "flow": "PUT HEAVY",
      "flowCls": "nogo"
    },
    {
      "t": "CAT",
      "gex": -5.3,
      "gexProxy": false,
      "flip": 900.0,
      "flipSrc": "oi-atm",
      "call": 41,
      "put": 59,
      "callOI": 13221,
      "putOI": 22620,
      "callVol": 1038,
      "putVol": 1140,
      "dte": 37,
      "exp": "2026-08-21",
      "price": 911.42,
      "flow": "PUT HEAVY",
      "flowCls": "nogo"
    },
    {
      "t": "GEV",
      "gex": -5.4,
      "gexProxy": false,
      "flip": 540.0,
      "flipSrc": "gamma",
      "call": 46,
      "put": 54,
      "callOI": 5591,
      "putOI": 9822,
      "callVol": 917,
      "putVol": 599,
      "dte": 37,
      "exp": "2026-08-21",
      "price": 1051.47,
      "flow": "PUT HEAVY",
      "flowCls": "nogo"
    },
    {
      "t": "VRT",
      "gex": -6.3,
      "gexProxy": false,
      "flip": 330.0,
      "flipSrc": "oi-atm",
      "call": 26,
      "put": 74,
      "callOI": 15890,
      "putOI": 45936,
      "callVol": 766,
      "putVol": 2045,
      "dte": 37,
      "exp": "2026-08-21",
      "price": 301.81,
      "flow": "PUT HEAVY",
      "flowCls": "nogo"
    },
    {
      "t": "XLB",
      "gex": -7.1,
      "gexProxy": false,
      "flip": 40.0,
      "flipSrc": "gamma",
      "call": 24,
      "put": 76,
      "callOI": 7304,
      "putOI": 103542,
      "callVol": 43,
      "putVol": 44,
      "dte": 37,
      "exp": "2026-08-21",
      "price": 50.51,
      "flow": "PUT HEAVY",
      "flowCls": "nogo"
    },
    {
      "t": "WMT",
      "gex": -16.0,
      "gexProxy": false,
      "flip": 80.0,
      "flipSrc": "gamma",
      "call": 40,
      "put": 60,
      "callOI": 52638,
      "putOI": 108012,
      "callVol": 2754,
      "putVol": 2643,
      "dte": 37,
      "exp": "2026-08-21",
      "price": 113.72,
      "flow": "PUT HEAVY",
      "flowCls": "nogo"
    },
    {
      "t": "XLI",
      "gex": -16.1,
      "gexProxy": false,
      "flip": 166.0,
      "flipSrc": "oi-atm",
      "call": 20,
      "put": 80,
      "callOI": 6786,
      "putOI": 55140,
      "callVol": 271,
      "putVol": 516,
      "dte": 37,
      "exp": "2026-08-21",
      "price": 179.98,
      "flow": "PUT HEAVY",
      "flowCls": "nogo"
    },
    {
      "t": "MU",
      "gex": -21.2,
      "gexProxy": false,
      "flip": 1000.0,
      "flipSrc": "oi-atm",
      "call": 44,
      "put": 56,
      "callOI": 130610,
      "putOI": 201304,
      "callVol": 18688,
      "putVol": 17584,
      "dte": 37,
      "exp": "2026-08-21",
      "price": 911.29,
      "flow": "PUT HEAVY",
      "flowCls": "nogo"
    },
    {
      "t": "SMH",
      "gex": -141.3,
      "gexProxy": false,
      "flip": 600.0,
      "flipSrc": "oi-atm",
      "call": 27,
      "put": 73,
      "callOI": 96830,
      "putOI": 298440,
      "callVol": 3103,
      "putVol": 7027,
      "dte": 37,
      "exp": "2026-08-21",
      "price": 587.41,
      "flow": "PUT HEAVY",
      "flowCls": "nogo"
    },
    {
      "t": "IWM",
      "gex": -248.8,
      "gexProxy": false,
      "flip": 280.0,
      "flipSrc": "oi-atm",
      "call": 21,
      "put": 79,
      "callOI": 205927,
      "putOI": 596258,
      "callVol": 22442,
      "putVol": 139708,
      "dte": 37,
      "exp": "2026-08-21",
      "price": 296.28,
      "flow": "PUT HEAVY",
      "flowCls": "nogo"
    },
    {
      "t": "SPY",
      "gex": -576.3,
      "gexProxy": false,
      "flip": 730.0,
      "flipSrc": "oi-atm",
      "call": 19,
      "put": 81,
      "callOI": 536997,
      "putOI": 1788656,
      "callVol": 30403,
      "putVol": 193273,
      "dte": 37,
      "exp": "2026-08-21",
      "price": 754.13,
      "flow": "PUT HEAVY",
      "flowCls": "nogo"
    },
    {
      "t": "HYG",
      "gex": -580.7,
      "gexProxy": false,
      "flip": 79.0,
      "flipSrc": "oi-atm",
      "call": 25,
      "put": 75,
      "callOI": 353070,
      "putOI": 1271893,
      "callVol": 9566,
      "putVol": 23628,
      "dte": 37,
      "exp": "2026-08-21",
      "price": 79.8,
      "flow": "PUT HEAVY",
      "flowCls": "nogo"
    },
    {
      "t": "QQQ",
      "gex": -597.9,
      "gexProxy": false,
      "flip": 680.0,
      "flipSrc": "oi-atm",
      "call": 41,
      "put": 59,
      "callOI": 372775,
      "putOI": 591585,
      "callVol": 27171,
      "putVol": 36726,
      "dte": 37,
      "exp": "2026-08-21",
      "price": 717.11,
      "flow": "PUT HEAVY",
      "flowCls": "nogo"
    }
  ]
}